Workbook

Sheet Ponts
C2: A consolider | Y2: A consolider
C3: EVS passée | Y3: EVS passée
C4: En cas D'EVS négatif (changement pont) | Y4: En cas D'EVS négatif (changement pont)
C5: Travaux spécifiques | Y5: Travaux spécifiques
C6: RGE 25 ans | Y6: RGE 25 ans
C7: RGE 50 ans | Y7: RGE 50 ans
C8: EVS + tx suite EVS (réparation type soudures) | Y8: EVS + tx suite EVS (réparation type soudures) OU dépenses obso (ex télécommandes)
B9: En Euros | N9: NEW ! | O9: NEW ! | P9: Evaluation Speciale | S9: OPEX usine = EVS + RGM après EVS + RGE après EVS (RGE "50 ans") CAPEX = RGE 25 ans + Installation nouveaux ponts (si EVS négatif) | BJ9: =COUNTA(BJ11:BJ185) -> 147 | BK9: ROADMAP SECURISATION DES PONTS
A10: PAYS | B10: Site | C10: Pont | D10: ACCESSOIRES : Pince ou Elingue | E10: EGT | F10: EGT € | G10: COMMENTAIRES | H10: Ligne de Presse ou utilisation | I10: MES | J10: Observations | K10: Age | L10: PRIX NEUF | M10: Travaux RG ou Installation Nouveau Pont | N10: Pont à évaluer en interne par Référent Levage (MES>2008) | O10: Année Evaluation Interne | P10: Evaluation Spéciale O/N | Q10: EVS Année | R10: E/S Montant | S10: 2024 EGT | T10: 2025 OPEX DF (EVS et travaux préconisés) (EVS et travaux préconisés) | U10: 2025 RGE/RGM CAPEX IV | V10: 2025 ACHAT NEUF CAPEX IV | W10: 2026 OPEX DF (EVS et travaux préconisés) | X10: 2026 RGE/RGM CAPEX IV | Y10: 2026 ACHAT NEUF CAPEX IV | Z10: 2027 OPEX DF (EVS et travaux préconisés) | AA10: 2027 RGE/RGM CAPEX IV | AB10: 2027 ACHAT NEUF CAPEX IV | AC10: 2028 OPEX DF (EVS et travaux préconisés) | AD10: 2028 RGE/RGM CAPEX IV | AE10: 2028 ACHAT NEUF CAPEX IV | AF10: 2029 OPEX DF (EVS et travaux préconisés) | AG10: 2029 RGE/RGM CAPEX IV | AH10: 2029 ACHAT NEUF CAPEX IV | AI10: 2030 OPEX DF (EVS et travaux préconisés) | AJ10: 2030 RGE/RGM CAPEX IV | AK10: 2030 ACHAT NEUF CAPEX IV | AL10: 2031 OPEX DF (EVS et travaux préconisés) | AM10: 2031 RGE/RGM CAPEX IV | AN10: 2031 ACHAT NEUF CAPEX IV | AO10: 2032 OPEX DF (EVS et travaux préconisés) | AP10: 2032 RGE/RGM CAPEX IV | AQ10: 2032 ACHAT NEUF CAPEX IV | AR10: 2033 OPEX DF (EVS et travaux préconisés) | AS10: 2033 RGE/RGM CAPEX IV | AT10: 2033 ACHAT NEUF CAPEX IV | AU10: 2034 OPEX DF (EVS et travaux préconisés) | AV10: 2034 RGE/RGM CAPEX IV | AW10: 2034 ACHAT NEUF CAPEX IV | AX10: 2035 OPEX DF (EVS et travaux préconisés) | AY10: 2035 RGE/RGM CAPEX IV | AZ10: 2035 ACHAT NEUF CAPEX IV | BA10: 2036 OPEX DF (EVS et travaux préconisés) | BB10: 2036 RGE/RGM CAPEX IV | BC10: 2036 ACHAT NEUF CAPEX IV | BD10: 2037 OPEX DF (EVS et travaux préconisés) | BE10: 2037 RGE/RGM CAPEX IV | BF10: 2037 ACHAT NEUF CAPEX IV | BK10: USAGE : Manutention et/ou Manipulation | BL10: TYPE : Automate ou Electromécanique | BM10: ROADMAP Capex Obsolescence | BN10: ROADMAP SECURISATION
A11: 1-FRANCE | B11: Chassis | C11: Pont E4 20T 48444 SEVAL/OMIS | I11: 2012 | J11: HORS SCOPE DEPT EMB | K11: =IF(I11="","",YEAR(TODAY())-I11) -> 14 | N11: =IF(I11>2008,"Evaluation interne", " ") -> Evaluation interne | O11: =IF(I11>2008, I11+20, " ") -> 2032 | P11: N | Q11: =I11+39 -> 2051 | R11: 40000 | BJ11: Pont E4 20T 48444 SEVAL/OMIS
A12: 1-FRANCE | B12: Chassis | C12: Pont E0 46833 25 T KONECRANES | I12: 2010 | J12: HORS SCOPE DEPT EMB | K12: =IF(I12="","",YEAR(TODAY())-I12) -> 16 | M12: RGE | N12: =IF(I12>2008,"Evaluation interne", " ") -> Evaluation interne | O12: =IF(I12>2008, I12+20, " ") -> 2030 | P12: N | Q12: =I12+39 -> 2049 | R12: 40000 | AX12: 40000 | BJ12: Pont E0 46833 25 T KONECRANES | BM12: 2035
A13: 1-FRANCE | B13: Chassis | C13: SP HH3 44839 25T ADC | I13: 2008 | J13: HORS SCOPE DEPT EMB | K13: =IF(I13="","",YEAR(TODAY())-I13) -> 18 | M13: RGE | N13: =IF(I13>2008,"Evaluation interne", " ") | O13: =IF(I13>2008, I13+20, " ") | P13: N | Q13: =I13+39 -> 2047 | R13: 25000 | AR13: 50000 | BJ13: SP HH3 44839 25T ADC | BK13: Manipulation | BM13: 2033
A14: 1-FRANCE | B14: Chassis | C14: Pont E2 1470200822 4T SEVAL | I14: 2003 | J14: HORS SCOPE DEPT EMB | K14: =IF(I14="","",YEAR(TODAY())-I14) -> 23 | N14: =IF(I14>2008,"Evaluation interne", " ") | O14: =IF(I14>2008, I14+20, " ") | P14: N | Q14: =I14+39 -> 2042 | R14: 40000 | BJ14: Pont E2 1470200822 4T SEVAL
A15: 1-FRANCE | B15: Chassis | C15: Pont E2' 1470200821 8/8 T DEMAG | I15: 2003 | J15: HORS SCOPE DEPT EMB | K15: =IF(I15="","",YEAR(TODAY())-I15) -> 23 | N15: =IF(I15>2008,"Evaluation interne", " ") | O15: =IF(I15>2008, I15+20, " ") | P15: N | Q15: =I15+39 -> 2042 | R15: 40000 | BJ15: Pont E2' 1470200821 8/8 T DEMAG
A16: 1-FRANCE | B16: Chassis | C16: Pont E2 1470200820 14/14 T SEVAL | I16: 2003 | J16: HORS SCOPE DEPT EMB | K16: =IF(I16="","",YEAR(TODAY())-I16) -> 23 | M16: RGE | N16: =IF(I16>2008,"Evaluation interne", " ") | O16: =IF(I16>2008, I16+20, " ") | P16: N | Q16: =I16+39 -> 2042 | R16: 40000 | AF16: 40000 | BJ16: Pont E2 1470200820 14/14 T SEVAL | BM16: 2029
A17: 1-FRANCE | B17: Chassis | C17: Pont (SP ?) E4 1470200756 8T | I17: 2003 | J17: HORS SCOPE DEPT EMB | K17: =IF(I17="","",YEAR(TODAY())-I17) -> 23 | M17: RGE | N17: =IF(I17>2008,"Evaluation interne", " ") | O17: =IF(I17>2008, I17+20, " ") | P17: N | Q17: =I17+39 -> 2042 | R17: 40000 | AC17: 20000 | BJ17: Pont (SP ?) E4 1470200756 8T | BM17: 2028
A18: 1-FRANCE | B18: Chassis | C18: Pont E5 25 T 1470200554 SEVAL | I18: 2003 | J18: HORS SCOPE DEPT EMB | K18: =IF(I18="","",YEAR(TODAY())-I18) -> 23 | M18: RGE | N18: =IF(I18>2008,"Evaluation interne", " ") | O18: =IF(I18>2008, I18+20, " ") | P18: N | Q18: =I18+39 -> 2042 | R18: 40000 | AC18: 50000 | BJ18: Pont E5 25 T 1470200554 SEVAL | BM18: 2028
A19: 1-FRANCE | B19: Chassis | C19: Pont E6 1470000240 50T SAMETO | I19: 2001 | J19: HORS SCOPE DEPT EMB | K19: =IF(I19="","",YEAR(TODAY())-I19) -> 25 | M19: RGE 25 ans | N19: =IF(I19>2008,"Evaluation interne", " ") | O19: =IF(I19>2008, I19+20, " ") | P19: N | Q19: =I19+39 -> 2040 | R19: 40000 | AA19: 170000 | BJ19: Pont E6 1470000240 50T SAMETO | BM19: 2027 | BN19: 2025
A20: 1-FRANCE | B20: Chassis | C20: Pont E6 1470001297 50/50T SAMETO | I20: 2001 | J20: HORS SCOPE DEPT EMB | K20: =IF(I20="","",YEAR(TODAY())-I20) -> 25 | M20: RGE 25 ans | N20: =IF(I20>2008,"Evaluation interne", " ") | O20: =IF(I20>2008, I20+20, " ") | P20: N | Q20: =I20+39 -> 2040 | R20: 40000 | AA20: 170000 | BJ20: Pont E6 1470001297 50/50T SAMETO | BM20: 2027
A21: 1-FRANCE | B21: Chassis | C21: Pont E0 1470000704 25 T SEVAL | I21: 2000 | J21: HORS SCOPE DEPT EMB | K21: =IF(I21="","",YEAR(TODAY())-I21) -> 26 | M21: RGE | N21: =IF(I21>2008,"Evaluation interne", " ") | O21: =IF(I21>2008, I21+20, " ") | P21: N | Q21: =I21+39 -> 2039 | R21: 40000 | X21: 150000 | BJ21: Pont E0 1470000704 25 T SEVAL | BM21: 2026
A22: 1-FRANCE | B22: Chassis | C22: Pont E2 1479900509 16T SAMETO | I22: 1999 | J22: HORS SCOPE DEPT EMB | K22: =IF(I22="","",YEAR(TODAY())-I22) -> 27 | M22: RGE | N22: =IF(I22>2008,"Evaluation interne", " ") | O22: =IF(I22>2008, I22+20, " ") | P22: N | Q22: =I22+39 -> 2038 | R22: 40000 | X22: 120000 | BJ22: Pont E2 1479900509 16T SAMETO | BM22: 2026
A23: 1-FRANCE | B23: Chassis | C23: Pont E1 759847 20T SAMETO | I23: 1994 | J23: HORS SCOPE DEPT EMB | K23: =IF(I23="","",YEAR(TODAY())-I23) -> 32 | M23: RGE | N23: =IF(I23>2008,"Evaluation interne", " ") | O23: =IF(I23>2008, I23+20, " ") | P23: N | Q23: =I23+39 -> 2033 | R23: 40000 | X23: 150000 | BJ23: Pont E1 759847 20T SAMETO | BM23: 2026
A24: 1-FRANCE | B24: Chassis | C24: Pont E1 759848 20/20 T SAMETO (RGE 2019) | I24: 1994 | J24: HORS SCOPE DEPT EMB | K24: =IF(I24="","",YEAR(TODAY())-I24) -> 32 | N24: =IF(I24>2008,"Evaluation interne", " ") | O24: =IF(I24>2008, I24+20, " ") | P24: N | Q24: =I24+39 -> 2033 | R24: 40000 | BJ24: Pont E1 759848 20/20 T SAMETO (RGE 2019)
A25: 1-FRANCE | B25: LHA | C25: Pont J12 63T | D25: Pince | H25: L08 | I25: 2006 | K25: =IF(I25="","",YEAR(TODAY())-I25) -> 20 | L25: ='DEMARCHE EVS'!B9 -> 950000 | M25: RGE | N25: =IF(I25>2008,"Evaluation interne", " ") | O25: =IF(I25>2008, I25+20, " ") | P25: NC | Q25: =I25+39 -> 2045 | R25: 40000 | AC25: 60000 | BJ25: Pont J12 | BM25: 2028
A26: 1-FRANCE | B26: LHA | C26: Pont J11 63T | D26: Pince | H26: L11 | I26: 2006 | K26: =IF(I26="","",YEAR(TODAY())-I26) -> 20 | M26: RGE | N26: =IF(I26>2008,"Evaluation interne", " ") | O26: =IF(I26>2008, I26+20, " ") | Q26: =I26+39 -> 2045 | R26: 40000 | AM26: 170000 | BJ26: Pont J11 | BM26: 2029
A27: 1-FRANCE | B27: LHA | C27: Pince outils J11 | D27: PINCE | H27: L11 | I27: 1999 | K27: =IF(I27="","",YEAR(TODAY())-I27) -> 27 | M27: RG | N27: =IF(I27>2008,"Evaluation interne", " ") | O27: =IF(I27>2008, I27+20, " ") | P27: NC | U27: 100000
A28: 1-FRANCE | B28: LHA | C28: Pince à outil J12 | D28: PINCE | H28: STOCKAGE | I28: 1999 | K28: =IF(I28="","",YEAR(TODAY())-I28) -> 27 | L28: 220000 | M28: RGM | N28: =IF(I28>2008,"Evaluation interne", " ") | O28: =IF(I28>2008, I28+20, " ") | P28: NC | X28: 85000
A29: 1-FRANCE | B29: LHA | C29: Pont J3 63/63T CAILLARD | D29: Elingue | H29: MAP/MAINTENANCE | I29: 1970 | J29: RGE 1998 | K29: =IF(I29="","",YEAR(TODAY())-I29) -> 56 | L29: 1170000 | M29: 2026 prov pour travaux / Installation nouveaux ponts 2027 | N29: =IF(I29>2008,"Evaluation interne", " ") | O29: =IF(I29>2008, I29+20, " ") | P29: N | Q29: 2026 | R29: 40000 | W29: 69000 | AA29: 170000 | AE29: 1170000 | BJ29: Pont J3 63/63T CAILLARD | BM29: 2026
A30: 1-FRANCE | B30: LHA | C30: Semi-portique N°1 J3 CHSL HUGO 10T | D30: Elingue | H30: MAP/MAINTENANCE | I30: 1979 | K30: =IF(I30="","",YEAR(TODAY())-I30) -> 47 | L30: 120000 | M30: RG | N30: =IF(I30>2008,"Evaluation interne", " ") | O30: =IF(I30>2008, I30+20, " ") | P30: N | Q30: 2026 | R30: 20000 | W30: 20000 | BJ30: Semi-portique N°1 J3 CHSL | BK30: Manipulation
A31: 1-FRANCE | B31: LHA | C31: Semi-portique N°2 J3 CHSL (10T SAMETO?)-STOP 06/02 | D31: Elingue | H31: MAP/MAINTENANCE | I31: 1979 | J31: RGE 2003 | K31: =IF(I31="","",YEAR(TODAY())-I31) -> 47 | L31: 120000 | M31: RG | N31: =IF(I31>2008,"Evaluation interne", " ") | O31: =IF(I31>2008, I31+20, " ") | P31: N | Q31: 2026 | R31: 20000 | W31: =20000 -> 20000 | BJ31: Semi-portqiue N°2 J3 CHSL | BK31: Manipulation
A32: 1-FRANCE | B32: LHA | C32: Pont J1sud 63T CAILLARD | H32: 80%OUTILS / 20%BOBINES | I32: 1970 | K32: =IF(I32="","",YEAR(TODAY())-I32) -> 56 | M32: RGE 50 ans | N32: =IF(I32>2008,"Evaluation interne", " ") | O32: =IF(I32>2008, I32+20, " ") | P32: O | Q32: 2035 | R32: 40000 | T32: =40000 + 25000 -> 65000 | AA32: 170000 | AX32: 40000 | BC32: 1120000 | BJ32: Pont J1sud 63T | BM32: 2026
A33: 1-FRANCE | B33: LHA | C33: J1 Nord | D33: Pince | H33: STOCKAGE | K33: =IF(I33="","",YEAR(TODAY())-I33) | N33: =IF(I33>2008,"Evaluation interne", " ") | O33: =IF(I33>2008, I33+20, " ") | BJ33: J1 Nord
A34: 1-FRANCE | B34: LHA | C34: J2 Nord | D34: Elingue | E34: 2027 | F34: 80000 | H34: STOCKAGE | K34: =IF(I34="","",YEAR(TODAY())-I34) | N34: =IF(I34>2008,"Evaluation interne", " ") | O34: =IF(I34>2008, I34+20, " ") | BJ34: J2 Nord | BN34: 2025
A35: 1-FRANCE | B35: LHA | C35: J2 Sud | D35: Elingue | E35: 2026 | F35: 80000 | H35: PAL/PAVAR | K35: =IF(I35="","",YEAR(TODAY())-I35) | N35: =IF(I35>2008,"Evaluation interne", " ") | O35: =IF(I35>2008, I35+20, " ") | BJ35: J2 Sud
A36: 1-FRANCE | B36: MCA | C36: Pont 63T XLHS SECAL | D36: Pince | H36: XL HS | I36: 2019 | K36: =IF(I36="","",YEAR(TODAY())-I36) -> 7 | N36: =IF(I36>2008,"Evaluation interne", " ") -> Evaluation interne | O36: =IF(I36>2008, I36+20, " ") -> 2039 | P36: N | Q36: =I36+20 -> 2039 | R36: 40000 | AD36: 140000 | BJ36: Pont 63T XLHS SECAL | BM36: 2028
A37: 1-FRANCE | B37: MCA | C37: PINCE 50T XXL HS | H37: XXL HS | I37: 2019 | K37: =IF(I37="","",YEAR(TODAY())-I37) -> 7 | N37: =IF(I37>2008,"Evaluation interne", " ") -> Evaluation interne | O37: =IF(I37>2008, I37+20, " ") -> 2039 | Q37: 2039
A38: 1-FRANCE | B38: MCA | C38: Pont 50/50 T XLHS SECAL | D38: Pince | H38: MAP XL | I38: 2019 | K38: =IF(I38="","",YEAR(TODAY())-I38) -> 7 | N38: =IF(I38>2008,"Evaluation interne", " ") -> Evaluation interne | O38: =IF(I38>2008, I38+20, " ") -> 2039 | P38: N | Q38: =I38+39 -> 2058 | R38: 40000 | AG38: 170000 | BJ38: Pont 50/50 T XLHS SECAL | BM38: 2029
A39: 1-FRANCE | B39: MCA | C39: Pont 25 T PAL SEVAL | D39: Elingue | E39: EGT | H39: PAL | I39: 2001 | K39: =IF(I39="","",YEAR(TODAY())-I39) -> 25 | M39: RGE 25 ans | N39: =IF(I39>2008,"Evaluation interne", " ") | O39: =IF(I39>2008, I39+20, " ") | P39: N | Q39: =I39+39 -> 2040 | R39: 40000 | U39: 135000 | Y39: 290000 | BJ39: Pont 25 T PAL SEVAL | BM39: 2025
A40: 1-FRANCE | B40: MCA | C40: Pont 32 T Appro bobines SAMETO | D40: Pince | H40: BOBINES | I40: 2000 | K40: =IF(I40="","",YEAR(TODAY())-I40) -> 26 | M40: RGE 25 ans | N40: =IF(I40>2008,"Evaluation interne", " ") | O40: =IF(I40>2008, I40+20, " ") | P40: N | Q40: =I40+39 -> 2039 | R40: 40000 | AD40: 170000 | BJ40: Pont 32 T Appro bobines SAMETO | BM40: 2027
A41: 1-FRANCE | B41: MCA | C41: Pont 25/25T Nord SAMETO | D41: Elingue | H41: MAP (et ex L3) | I41: 1998 | K41: =IF(I41="","",YEAR(TODAY())-I41) -> 28 | M41: RGE 25 ans | N41: =IF(I41>2008,"Evaluation interne", " ") | O41: =IF(I41>2008, I41+20, " ") | P41: N | Q41: =I41+39 -> 2037 | R41: 40000 | AA41: 0 | BJ41: Pont 25/25T Nord SAMETO | BM41: 2025 | BN41: 2025
A42: 1-FRANCE | B42: MCA | C42: Semi-portique 25/25 T surclassé 30T SEVAL | H42: MAP/travée 5400T | I42: 1996 | K42: =IF(I42="","",YEAR(TODAY())-I42) -> 30 | M42: RGE 25 ans | N42: =IF(I42>2008,"Evaluation interne", " ") | O42: =IF(I42>2008, I42+20, " ") | P42: N | Q42: 2035 | R42: 25000 | AA42: 170000 | BJ42: Semi-portique 25/25 T surclassé 30T SEVAL | BM42: 2026
A43: 1-FRANCE | B43: MCA | C43: Pont 80T SAMETO | D43: Pince | H43: PT5400 | I43: 1995 | K43: =IF(I43="","",YEAR(TODAY())-I43) -> 31 | M43: RGE 25 ans | N43: =IF(I43>2008,"Evaluation interne", " ") | O43: =IF(I43>2008, I43+20, " ") | P43: N | Q43: 2034 | R43: 40000 | AA43: 0 | BJ43: Pont 80T SAMETO | BM43: 2026
A44: 1-FRANCE | B44: MCA | C44: Pont 25/25 T Sud SEVAL L01 | D44: Elingue | E44: 2027 | F44: 80000 | H44: L01 | I44: 1994 | K44: =IF(I44="","",YEAR(TODAY())-I44) -> 32 | M44: RGE 25 ans | N44: =IF(I44>2008,"Evaluation interne", " ") | O44: =IF(I44>2008, I44+20, " ") | P44: N | Q44: 2033 | R44: 40000 | AA44: 170000 | BJ44: Pont 25/25 T Sud SEVAL | BM44: 2027
A45: 1-FRANCE | B45: UGB | C45: Pont A1 GE 35 T SECAL | D45: Pince | H45: BOBINES | I45: 2016 | K45: =IF(I45="","",YEAR(TODAY())-I45) -> 10 | N45: =IF(I45>2008,"Evaluation interne", " ") -> Evaluation interne | O45: =IF(I45>2008, I45+20, " ") -> 2036 | P45: N | Q45: =I45+39 -> 2055 | R45: 40000 | BJ45: Pont A1 GE 35 T SECAL | BM45: Pince
A46: 1-FRANCE | B46: UGB | C46: Pont A1 PE 35 T KONECRANES | D46: Pince | H46: BOBINES | I46: 2010 | K46: =IF(I46="","",YEAR(TODAY())-I46) -> 16 | M46: RGE 25 ans | N46: =IF(I46>2008,"Evaluation interne", " ") -> Evaluation interne | O46: =IF(I46>2008, I46+20, " ") -> 2030 | P46: N | Q46: =I46+39 -> 2049 | R46: 40000 | AI46: 40000 | AY46: 170000 | BJ46: Pont A1 PE 35 T KONECRANES | BM46: 2035
A47: 1-FRANCE | B47: UGB | C47: Pont A2 GE 35 T KONECRANES | D47: Elingue | E47: EGT | H47: DECOUPES | I47: 2008 | K47: =IF(I47="","",YEAR(TODAY())-I47) -> 18 | M47: RGE 25 ans | N47: =IF(I47>2008,"Evaluation interne", " ") | O47: =IF(I47>2008, I47+20, " ") | P47: N | Q47: =I47+39 -> 2047 | R47: 40000 | AS47: 170000 | BJ47: Pont A2 GE 35 T KONECRANES | BM47: 2033
A48: 1-FRANCE | B48: UGB | C48: Pont A2 PE 35 T KONECRANES | D48: Elingue | E48: EGT | H48: DECOUPES | I48: 2006 | K48: =IF(I48="","",YEAR(TODAY())-I48) -> 20 | M48: RGE 25 ans | N48: =IF(I48>2008,"Evaluation interne", " ") | O48: =IF(I48>2008, I48+20, " ") | P48: N | Q48: =I48+39 -> 2045 | R48: 40000 | AM48: 170000 | BJ48: Pont A2 PE 35 T KONECRANES | BM48: 2031
A49: 1-FRANCE | B49: UGB | C49: Pont A2 50 T SAMETO | D49: Elingue | E49: 2026 | F49: 80000 | G49: défini FD/DD/ER arbitrairement le 21/04, sera présenté au CdD par Florian | H49: PAL340 | I49: 2001 | J49: AC installé en 2018 suite usure galets | K49: =IF(I49="","",YEAR(TODAY())-I49) -> 25 | M49: RGE 25 ans | N49: =IF(I49>2008,"Evaluation interne", " ") | O49: =IF(I49>2008, I49+20, " ") | P49: N | Q49: =I49+39 -> 2040 | R49: 40000 | AD49: 170000 | BJ49: Pont A2 50 T SAMETO | BM49: 2027
A50: 1-FRANCE | B50: UGB | C50: Pont A7 63/63 T SEVAL | D50: Elingue | E50: EGT | H50: STOCKAGE | I50: 2004 | K50: =IF(I50="","",YEAR(TODAY())-I50) -> 22 | M50: RGE 25 ans | N50: =IF(I50>2008,"Evaluation interne", " ") | O50: =IF(I50>2008, I50+20, " ") | P50: N | Q50: =I50+39 -> 2043 | R50: 40000 | AG50: 170000 | BJ50: Pont A7 63/63 T SEVAL | BM50: 2029
A51: 1-FRANCE | B51: UGB | C51: Pont A8 63/63 T SAMETO | D51: Elingue | E51: EGT | H51: L12 | I51: 2001 | K51: =IF(I51="","",YEAR(TODAY())-I51) -> 25 | L51: 1170000 | M51: RGE 25 ans | N51: =IF(I51>2008,"Evaluation interne", " ") | O51: =IF(I51>2008, I51+20, " ") | P51: N | Q51: =I51+39 -> 2040 | R51: 40000 | AA51: 0 | AG51: 170000 | BJ51: Pont A8 63/63 T SAMETO | BM51: 2026 | BN51: 2026 | BO51: était prévu 2025, budget 25 transféré à CVP
A52: 1-FRANCE | B52: UGB | C52: Pont A9 63/63 T KONECRANES | E52: NC | H52: MAINTENANCE/MAP | I52: 2005 | K52: =IF(I52="","",YEAR(TODAY())-I52) -> 21 | M52: RGE 25 ans | N52: =IF(I52>2008,"Evaluation interne", " ") | O52: =IF(I52>2008, I52+20, " ") | P52: N | Q52: =I52+39 -> 2044 | R52: 40000 | AJ52: 170000 | BJ52: Pont A9 63/63 T KONECRANES | BM52: 2030
A53: 1-FRANCE | B53: UGB | C53: Pont A10 63/63 T SAMETO | E53: EGT | H53: X L17 | I53: 1996 | K53: =IF(I53="","",YEAR(TODAY())-I53) -> 30 | M53: RGE 25 ans | N53: =IF(I53>2008,"Evaluation interne", " ") | O53: =IF(I53>2008, I53+20, " ") | P53: N | Q53: =I53+39 -> 2035 | R53: 40000 | AA53: 170000 | BJ53: Pont A10 63/63 T SAMETO | BM53: 2027
A54: 1-FRANCE | B54: UGB | C54: Pont A11 63/63 T CAILLARD/SAMETO ? | E54: EGT | H54: HO | I54: 1974 | J54: RGE 2000 | K54: =IF(I54="","",YEAR(TODAY())-I54) -> 52 | L54: 1170000 | M54: RGE 25 ans | N54: =IF(I54>2008,"Evaluation interne", " ") | O54: =IF(I54>2008, I54+20, " ") | P54: N | Q54: 2026 | R54: 40000 | W54: =40000 + 40000 -> 80000 | AA54: 170000 | BJ54: Pont A11 63/63 T CAILLARD/SAMETO ? | BM54: 2027 | BQ54: >2027
A55: 1-FRANCE | B55: UGB | C55: Pont A12 Caillard/SAMETO 63 T | D55: Elingue | E55: 2027 | H55: L21 | I55: 1974 | J55: RGE 1999 | K55: =IF(I55="","",YEAR(TODAY())-I55) -> 52 | L55: ='DEMARCHE EVS'!B9 -> 950000 | M55: RGE | N55: =IF(I55>2008,"Evaluation interne", " ") | O55: =IF(I55>2008, I55+20, " ") | P55: N | Q55: 2027 | R55: 40000 | T55: 60000 | W55: 160000 | Z55: 40000 | AE55: 900000 | BJ55: Pont A12 Caillard/SAMETO 63 T | BM55: 2028 | BN55: 2025 | BQ55: 2025
A56: 1-FRANCE | B56: UGB | C56: Pont A13 80 T SECAL/OMIS | D56: Pince | H56: PT5400 | I56: 2015 | K56: =IF(I56="","",YEAR(TODAY())-I56) -> 11 | N56: =IF(I56>2008,"Evaluation interne", " ") -> Evaluation interne | O56: =IF(I56>2008, I56+20, " ") -> 2035 | P56: N | Q56: =I56+39 -> 2054 | R56: 40000 | BJ56: Pont A13 80 T SECAL/OMIS
A57: 1-FRANCE | B57: UGB | C57: Pont A14 63/63 T ADC | E57: NC | H57: X MP | I57: 2019 | K57: =IF(I57="","",YEAR(TODAY())-I57) -> 7 | N57: =IF(I57>2008,"Evaluation interne", " ") -> Evaluation interne | O57: =IF(I57>2008, I57+20, " ") -> 2039 | P57: N | Q57: =I57+39 -> 2058 | R57: 40000 | BJ57: Pont A14 63/63 T ADC
A58: 1-FRANCE | B58: UGB | C58: Pont A15 50/50 T SEVAL/OMIS | E58: NC | H58: X | I58: 2012 | K58: =IF(I58="","",YEAR(TODAY())-I58) -> 14 | N58: =IF(I58>2008,"Evaluation interne", " ") -> Evaluation interne | O58: =IF(I58>2008, I58+20, " ") -> 2032 | P58: N | Q58: =I58+39 -> 2051 | R58: 40000 | BJ58: Pont A15 50/50 T SEVAL/OMIS
A59: 1-FRANCE | B59: UGB | C59: Pont A16 63/63 T SAMETO | E59: NC | H59: MAP | I59: 1993 | K59: =IF(I59="","",YEAR(TODAY())-I59) -> 33 | L59: 120000 | M59: RGE 25 ans | N59: =IF(I59>2008,"Evaluation interne", " ") | O59: =IF(I59>2008, I59+20, " ") | P59: N | Q59: =I59+39 -> 2032 | R59: 40000 | AD59: 170000 | BJ59: Pont A16 63/63 T SAMETO | BM59: 2028 | BQ59: Not Relevant
A60: 1-FRANCE | B60: UGB | C60: Semi-portique A16 10 T | E60: NC | I60: 1974 | K60: =IF(I60="","",YEAR(TODAY())-I60) -> 52 | M60: STOP-à remplacer par SP A15 | N60: =IF(I60>2008,"Evaluation interne", " ") | O60: =IF(I60>2008, I60+20, " ") | P60: O | Q60: 2025 | R60: 25000 | T60: =15000+25000 -> 40000 | BJ60: Semi-portique A16 10 T | BK60: Manipulation | BM60: 2026 | BQ60: 2026
A61: 1-FRANCE | B61: UGB | C61: Pont A17 35 T SEVAL/OMIS | H61: INJECTION | I61: 2009 | J61: HORS SCOPE DEPT EMB | K61: =IF(I61="","",YEAR(TODAY())-I61) -> 17 | N61: =IF(I61>2008,"Evaluation interne", " ") -> Evaluation interne | O61: =IF(I61>2008, I61+20, " ") -> 2029 | P61: N | Q61: =I61+39 -> 2048 | R61: 40000 | BJ61: Pont A17 35 T SEVAL/OMIS
A62: 1-FRANCE | B62: UGB | C62: Pont A18 CAILLARD 32/32T | H62: INJECTION | I62: 1974 | J62: HORS SCOPE DEPT EMB | K62: =IF(I62="","",YEAR(TODAY())-I62) -> 52 | L62: ='DEMARCHE EVS'!B6 -> 675000 | M62: Installation nouveaux ponts ou RGE | N62: =IF(I62>2008,"Evaluation interne", " ") | O62: =IF(I62>2008, I62+20, " ") | P62: O | Q62: 2031 | R62: 40000 | W62: 40000 | AA62: 170000 | BJ62: Pont A18 32/32T | BM62: 2027 | BQ62: 2027
A63: 1-FRANCE | B63: UPL | C63: Pont AA1 45 T SEVAL | D63: Elingue | E63: EGT | I63: 2005 | K63: =IF(I63="","",YEAR(TODAY())-I63) -> 21 | M63: RGE | N63: =IF(I63>2008,"Evaluation interne", " ") | O63: =IF(I63>2008, I63+20, " ") | P63: N | Q63: =I63+39 -> 2044 | R63: 40000 | AO63: 60000 | BJ63: Pont AA1 45 T SEVAL | BM63: 2032 | BQ63: COUT TOTAL : 40 K€
A64: 1-FRANCE | B64: UPL | C64: Pince outils AB2 | D64: Pince | H64: L21/24 | I64: 2005 | K64: =IF(I64="","",YEAR(TODAY())-I64) -> 21 | M64: RG | N64: =IF(I64>2008,"Evaluation interne", " ") | O64: =IF(I64>2008, I64+20, " ") | P64: NC | Q64: =I64+39 -> 2044 | R64: 40000 | AA64: 90000
A65: 1-FRANCE | B65: UPL | C65: Pince outils AB6 | D65: Pince | I65: 2005 | K65: =IF(I65="","",YEAR(TODAY())-I65) -> 21 | M65: RG | N65: =IF(I65>2008,"Evaluation interne", " ") | O65: =IF(I65>2008, I65+20, " ") | P65: NC | Q65: =I65+39 -> 2044 | AA65: 90000
A66: 1-FRANCE | B66: UPL | C66: Pont AB3 50T SAMETO | D66: Elingue | E66: EGT | I66: 2001 | K66: =IF(I66="","",YEAR(TODAY())-I66) -> 25 | L66: ='DEMARCHE EVS'!B8 -> 840000 | M66: RGE 25 ans | N66: =IF(I66>2008,"Evaluation interne", " ") | O66: =IF(I66>2008, I66+20, " ") | P66: N | Q66: =I66+39 -> 2040 | R66: 40000 | AJ66: 170000 | BJ66: Pont AB3 50T SAMETO | BM66: 2030 | BQ66: Briques Solution initiale :
A67: 1-FRANCE | B67: UPL | C67: Pont AA3 28T SEVAL | D67: Elingue | E67: EGT | I67: 2001 | K67: =IF(I67="","",YEAR(TODAY())-I67) -> 25 | L67: ='DEMARCHE EVS'!B6 -> 675000 | M67: RGE 25 ans | N67: =IF(I67>2008,"Evaluation interne", " ") | O67: =IF(I67>2008, I67+20, " ") | P67: N | Q67: =I67+39 -> 2040 | R67: 40000 | AJ67: 170000 | BJ67: Pont AA3 28T SEVAL | BM67: 2030 | BQ67: - Périmètres de sécurité
A68: 1-FRANCE | B68: UPL | C68: Pont AB1 43 T SEVAL | D68: Elingue | E68: EGT | H68: L12 | I68: 1997 | K68: =IF(I68="","",YEAR(TODAY())-I68) -> 29 | M68: RGE | N68: =IF(I68>2008,"Evaluation interne", " ") | O68: =IF(I68>2008, I68+20, " ") | P68: N | Q68: =I68+39 -> 2036 | R68: 40000 | BJ68: Pont AB1 43 T SEVAL | BM68: 2027 | BN68: 2025 | BO68: Confirmé Yannick | BQ68: Priorité 2 : ponts avec pinces (outils, bobines)
A69: 1-FRANCE | B69: UPL | C69: Pont AB2 40T SEVAL | D69: Pince | H69: L21/24 | I69: 1993 | J69: var transl faite, reste second crochet | K69: =IF(I69="","",YEAR(TODAY())-I69) -> 33 | M69: RGE 25 ans | N69: =IF(I69>2008,"Evaluation interne", " ") | O69: =IF(I69>2008, I69+20, " ") | P69: N | Q69: =I69+39 -> 2032 | R69: 40000 | AA69: 25000 | BJ69: Pont AB2 40T SEVAL | BM69: 2026 | BQ69: Priorité 1 : Pont Transfert Outil avec élingues
A70: 1-FRANCE | B70: UPL | C70: Pont AA5 28 T SEVAL | D70: Elingue | E70: 2027 | F70: 80000 | H70: STOCKAGE | I70: 1993 | K70: =IF(I70="","",YEAR(TODAY())-I70) -> 33 | M70: RGE 25 ans | N70: =IF(I70>2008,"Evaluation interne", " ") | O70: =IF(I70>2008, I70+20, " ") | P70: N | Q70: =I70+39 -> 2032 | R70: 40000 | AA70: 25000 | BJ70: Pont AA5 28 T SEVAL | BM70: 2026 | BQ70: Priorité 1bis : Pont Obso (RGE prévue ou changement de pont)
A71: 1-FRANCE | B71: UPL | C71: Pont AB5 40 T SEVAL | D71: Elingue | H71: MAP | I71: 1993 | K71: =IF(I71="","",YEAR(TODAY())-I71) -> 33 | M71: RGE 25 ans | N71: =IF(I71>2008,"Evaluation interne", " ") | O71: =IF(I71>2008, I71+20, " ") | P71: N | Q71: =I71+39 -> 2032 | R71: 40000 | Z71: 12000 | BJ71: Pont AB5 40 T SEVAL | BM71: asap | BQ71: 2024
A72: 1-FRANCE | B72: UPL | C72: Pont RAsud 32T CHSL | D72: Elingue | H72: STOCKAGE | I72: 1971 | J72: Projet pince 2026 en cours | K72: =IF(I72="","",YEAR(TODAY())-I72) -> 55 | L72: 850000 | M72: Installation nouveaux ponts | N72: =IF(I72>2008,"Evaluation interne", " ") | O72: =IF(I72>2008, I72+20, " ") | P72: O | Q72: 2024 | R72: 40000 | AI72: 40000 | AN72: 850000 | BJ72: Pont RAsud 32T CHSL | BM72: 2026
A73: 1-FRANCE | B73: UPL | C73: Pont RAcentre 32T CHSL | D73: Elingue | E73: EGT | H73: STOCKAGE | I73: 1971 | K73: =IF(I73="","",YEAR(TODAY())-I73) -> 55 | L73: 860000 | M73: Installation nouveaux ponts | N73: =IF(I73>2008,"Evaluation interne", " ") | O73: =IF(I73>2008, I73+20, " ") | P73: N | Q73: 2026 | R73: 40000 | W73: =40000 + 25000 -> 65000 | AB73: 860000 | BJ73: Pont RAcentre 32T CHSL | BM73: 2027 | BQ73: Eventgate : 15 K€ (facturé 18/20K€ par l'intégrateur)
A74: 1-FRANCE | B74: UPL | C74: Pont RA Nord 32T CHSL | D74: Elingue | E74: EGT | H74: STOCKAGE | I74: 1971 | K74: =IF(I74="","",YEAR(TODAY())-I74) -> 55 | L74: ='DEMARCHE EVS'!B6 -> 675000 | M74: Installation nouveaux ponts | N74: =IF(I74>2008,"Evaluation interne", " ") | O74: =IF(I74>2008, I74+20, " ") | P74: N | Q74: 2027 | R74: 40000 | Z74: =40000 + 25000 -> 65000 | AE74: 860000 | BJ74: Pont RA Nord 32T CHSL | BM74: 2028 | BQ74: Intégrateur : 20 K€
A75: 1-FRANCE | B75: UPL | C75: Pont AF3 32T SAMETO | H75: Stockage outils | I75: 1971 | K75: =IF(I75="","",YEAR(TODAY())-I75) -> 55 | L75: ='DEMARCHE EVS'!B6 -> 675000 | P75: N | Q75: 2026 | R75: 40,00 | W75: 40000 | AD75: 170000
A76: 1-FRANCE | B76: UPL | C76: Pont AB6. FLC/SAMETO. 50T | D76: Pince | H76: L62 | I76: 1969 | J76: rénovation en 2000 | K76: =IF(I76="","",YEAR(TODAY())-I76) -> 57 | L76: ='DEMARCHE EVS'!B8 -> 840000 | M76: RGE | N76: =IF(I76>2008,"Evaluation interne", " ") | O76: =IF(I76>2008, I76+20, " ") | P76: O | Q76: 2027 | R76: 40000 | T76: 50000 | Z76: 40000 | BJ76: Pont AB6. FLC/SAMETO. 50T | BK76: Manutention | BM76: 2025
A77: 1-FRANCE | B77: UPL | C77: Pont AA4 6T APPLEVAGE | D77: Elingue | H77: MAINTENANCE | I77: 1958 | K77: =IF(I77="","",YEAR(TODAY())-I77) -> 68 | L77: ='DEMARCHE EVS'!B4 -> 70000 | N77: =IF(I77>2008,"Evaluation interne", " ") | O77: =IF(I77>2008, I77+20, " ") | P77: O | Q77: 2025 | R77: 8000 | T77: 8000 | AI77: 8000 | BJ77: Pont AA4 6T APLEVAGE | BM77: asap | BQ77: Done
A78: 1-FRANCE | B78: UPL | C78: Pont AB4 Nord 15T APPLEVAGE | D78: Elingue | E78: EGT | H78: X | I78: 1958 | K78: =IF(I78="","",YEAR(TODAY())-I78) -> 68 | L78: 150000 | N78: =IF(I78>2008,"Evaluation interne", " ") | O78: =IF(I78>2008, I78+20, " ") | P78: O | Q78: 2028 | R78: 4300 | W78: 4300 | AC78: 4300 | BJ78: Pont AB4 Nord 15T APLEVAGE | BM78: asap
A79: 1-FRANCE | B79: UPL | C79: Pont AB4 sud 15T APPLEVAGE | D79: Elingue | H79: L43 MP | I79: 1957 | K79: =IF(I79="","",YEAR(TODAY())-I79) -> 69 | L79: 150000 | N79: =IF(I79>2008,"Evaluation interne", " ") | O79: =IF(I79>2008, I79+20, " ") | P79: O | Q79: 2028 | R79: 4300 | W79: 4300 | AC79: 4300 | BJ79: Pont AB4 sud 15T APLEVAGE | BM79: asap | BQ79: - Bouées de détection assymétrique
A80: 1-FRANCE | B80: UPL | C80: Pont AA2 6T LEVMAN | D80: Elingue | H80: RABOUTEUSES | I80: 1953 | K80: =IF(I80="","",YEAR(TODAY())-I80) -> 73 | N80: =IF(I80>2008,"Evaluation interne", " ") | O80: =IF(I80>2008, I80+20, " ") | P80: à désinvestir > sept 25 | BJ80: Pont AA2 6T LEVMAN | BM80: asap
A81: 2-ESPAGNE | B81: PAL | C81: SP 25/25T SEVAL | D81: Elingue | I81: 2006 | K81: =IF(I81="","",YEAR(TODAY())-I81) -> 20 | M81: RGE 25 ans | N81: =IF(I81>2008,"Evaluation interne", " ") | O81: =IF(I81>2008, I81+20, " ") | P81: N | Q81: =I81+39 -> 2045 | R81: 25000 | BJ81: SP 25/25T SEVAL | BK81: Manipulation | BM81: 2029
A82: 2-ESPAGNE | B82: PAL | C82: Pont 63/63T PG1 SEVAL Matriceria | D82: Elingue | H82: MAINTENANCE | I82: 2004 | K82: =IF(I82="","",YEAR(TODAY())-I82) -> 22 | M82: RGE 25 ans | N82: =IF(I82>2008,"Evaluation interne", " ") | O82: =IF(I82>2008, I82+20, " ") | P82: N | Q82: =I82+39 -> 2043 | R82: 40000 | Z82: 20000 | AP82: 170000 | BJ82: Pont 63/63T PG1 SEVAL Matriceria | BM82: 2027
A83: 2-ESPAGNE | B83: PAL | C83: Pont 63T PG2 SEVAL L2 | D83: Elingue | E83: EGT | H83: L02 | I83: 2002 | K83: =IF(I83="","",YEAR(TODAY())-I83) -> 24 | M83: RGE 25 ans | N83: =IF(I83>2008,"Evaluation interne", " ") | O83: =IF(I83>2008, I83+20, " ") | P83: N | Q83: =I83+39 -> 2041 | R83: 40000 | Z83: 20000 | AJ83: 170000 | BJ83: Pont 63T PG2 SEVAL L2 | BM83: 2026
A84: 2-ESPAGNE | B84: PAL | C84: Pont 63T PG3 SEVAL L3 et 4 | D84: Elingue | E84: EGT | F84: RPM S23 - att expertise | H84: L03/L04 | I84: 2002 | K84: =IF(I84="","",YEAR(TODAY())-I84) -> 24 | L84: 1100000 | M84: RGE 25 ans | N84: =IF(I84>2008,"Evaluation interne", " ") | O84: =IF(I84>2008, I84+20, " ") | P84: N | Q84: =I84+39 -> 2041 | R84: 40000 | X84: 329000 | Z84: 20000 | AJ84: 170000 | BJ84: Pont 63T PG3 SEVAL L3 et 4 | BM84: 2026
A85: 2-ESPAGNE | B85: PAL | C85: Pont 32/32T PG4 SEVAL | D85: Elingue | E85: EGT | I85: 2005 | K85: =IF(I85="","",YEAR(TODAY())-I85) -> 21 | M85: RGE 25 ans | N85: =IF(I85>2008,"Evaluation interne", " ") | O85: =IF(I85>2008, I85+20, " ") | P85: N | Q85: =I85+39 -> 2044 | R85: 40000 | Z85: 20000 | AS85: 170000 | BJ85: Pont 32/32T PG4 SEVAL | BM85: 2028
A86: 2-ESPAGNE | B86: PAL | C86: Pont 45/45T PG5 DEMAG High Speed | D86: Elingue | E86: EGT | H86: XL HS | I86: 2017 | K86: =IF(I86="","",YEAR(TODAY())-I86) -> 9 | N86: =IF(I86>2008,"Evaluation interne", " ") -> Evaluation interne | O86: =IF(I86>2008, I86+20, " ") -> 2037 | P86: N | Q86: =I86+20 -> 2037 | R86: 40000 | AV86: 170000 | BJ86: Pont 45/45T PG5 DEMAG High Speed | BN86: 2025
A87: 2-ESPAGNE | B87: PAL | C87: Pont 63/63T PG6 DEMAG | D87: Elingue | E87: EGT | I87: 2001 | K87: =IF(I87="","",YEAR(TODAY())-I87) -> 25 | M87: RGE 25 ans | N87: =IF(I87>2008,"Evaluation interne", " ") | O87: =IF(I87>2008, I87+20, " ") | P87: N | Q87: =I87+39 -> 2040 | R87: 40000 | Z87: 20000 | AG87: 170000 | BJ87: Pont 63/63T PG6 DEMAG | BM87: 2026
A88: 2-ESPAGNE | B88: PAL | C88: Pont 45/45T PG7 GH | D88: Elingue | E88: 2027 | F88: 83000 | I88: 2021 | K88: =IF(I88="","",YEAR(TODAY())-I88) -> 5 | N88: =IF(I88>2008,"Evaluation interne", " ") -> Evaluation interne | O88: =IF(I88>2008, I88+20, " ") -> 2041 | P88: N | Q88: =I88+39 -> 2060 | R88: 40000 | Z88: 20000 | BJ88: Pont 45/45T PG7 GH
A89: 2-ESPAGNE | B89: VLL | C89: Pont 40 T HOMANSER | E89: EGT | I89: 2021 | K89: =IF(I89="","",YEAR(TODAY())-I89) -> 5 | N89: =IF(I89>2008,"Evaluation interne", " ") -> Evaluation interne | O89: =IF(I89>2008, I89+20, " ") -> 2041 | P89: N | Q89: =I89+39 -> 2060 | R89: 40000 | BJ89: Pont 40 T HOMANSER
A90: 2-ESPAGNE | B90: VLL | C90: Pont 10 T HOMANSER | E90: EGT | H90: X | I90: 2021 | K90: =IF(I90="","",YEAR(TODAY())-I90) -> 5 | N90: =IF(I90>2008,"Evaluation interne", " ") -> Evaluation interne | O90: =IF(I90>2008, I90+20, " ") -> 2041 | P90: N | Q90: =I90+39 -> 2060 | R90: 40000 | BJ90: Pont 10 T HOMANSER
A91: 2-ESPAGNE | B91: VLL | C91: Pont 32 Tnord SEVAL bobines + retrofit DEMAG (2016) | D91: Pince | H91: BOBINES | I91: 2004 | K91: =IF(I91="","",YEAR(TODAY())-I91) -> 22 | M91: RG | N91: =IF(I91>2008,"Evaluation interne", " ") | O91: =IF(I91>2008, I91+20, " ") | P91: N | Q91: =I91+39 -> 2043 | R91: 40000 | U91: 110000 | AP91: 170000 | BJ91: Pont 32 Tnord SEVAL bobines + retrofit DEMAG (2016) | BM91: 2025
A92: 2-ESPAGNE | B92: VLL | C92: Pont 32Tsud SEVAL bobines + retrofit DEMAG (2011) | D92: Pince | H92: BOBINES | I92: 2004 | K92: =IF(I92="","",YEAR(TODAY())-I92) -> 22 | M92: RGE | N92: =IF(I92>2008,"Evaluation interne", " ") | O92: =IF(I92>2008, I92+20, " ") | P92: N | Q92: =I92+39 -> 2043 | R92: 40000 | U92: 110000 | AP92: 170000 | BJ92: Pont 32Tsud SEVAL bobines + retrofit DEMAG (2011) | BM92: 2025
A93: 2-ESPAGNE | B93: VLL | C93: Pont 63/63 T ARAEL L1 | D93: Elingue | E93: EGT | H93: L1 | I93: 2000 | K93: =IF(I93="","",YEAR(TODAY())-I93) -> 26 | M93: RGE | N93: =IF(I93>2008,"Evaluation interne", " ") | O93: =IF(I93>2008, I93+20, " ") | P93: N | Q93: =I93+39 -> 2039 | R93: 40000 | AD93: 170000 | BJ93: Pont 63/63 T ARAEL L1 | BM93: 2027
A94: 2-ESPAGNE | B94: VLL | C94: Pont 63/63 T SEVAL L3 | D94: Elingue | E94: EGT | H94: L3 | I94: 1998 | K94: =IF(I94="","",YEAR(TODAY())-I94) -> 28 | M94: RGE 25 ans | N94: =IF(I94>2008,"Evaluation interne", " ") | O94: =IF(I94>2008, I94+20, " ") | P94: N | Q94: =I94+39 -> 2037 | R94: 40000 | V94: A DECALER | AA94: 170000 | BJ94: Pont 63/63 T SEVAL L3 | BM94: 2026 | BO94: annulé au profit de L05/06
A95: 2-ESPAGNE | B95: VLL | C95: Pont 32/32 T SEVAL L5 | D95: Elingue | E95: 2026 | F95: 88000 | H95: L5/L6 | I95: 2001 | K95: =IF(I95="","",YEAR(TODAY())-I95) -> 25 | M95: RGE 25 ans | N95: =IF(I95>2008,"Evaluation interne", " ") | O95: =IF(I95>2008, I95+20, " ") | P95: N | Q95: =I95+39 -> 2040 | R95: 40000 | AG95: 170000 | BJ95: Pont 32/32 T SEVAL L5 | BM95: 2028 | BN95: 2025 | BO95: changement chef de dpt 16/04/25
A96: 2-ESPAGNE | B96: VLL | C96: Pont 32? 25?/32? 25 T ARAEL L7 | D96: Elingue | H96: MP L07 | I96: 1999 | K96: =IF(I96="","",YEAR(TODAY())-I96) -> 27 | M96: RGE 25 ans | N96: =IF(I96>2008,"Evaluation interne", " ") | O96: =IF(I96>2008, I96+20, " ") | P96: N | Q96: =I96+39 -> 2038 | R96: 40000 | V96: A DECALER | AA96: 170000 | BJ96: Pont 32? 25?/32? 25 T ARAEL L7 | BM96: 2026
A97: 2-ESPAGNE | B97: VLL | C97: Pont 63/63 T SEVAL L9 | D97: Elingue | E97: EGT | H97: L9 | I97: 2000 | K97: =IF(I97="","",YEAR(TODAY())-I97) -> 26 | M97: RGE | N97: =IF(I97>2008,"Evaluation interne", " ") | O97: =IF(I97>2008, I97+20, " ") | P97: N | Q97: =I97+39 -> 2039 | R97: 40000 | AD97: 170000 | BJ97: Pont 63/63 T SEVAL L9 | BM97: 2027
A98: 2-ESPAGNE | B98: VLL | C98: Pont 32/32 T SEVAL L11 | D98: Elingue | E98: EGT | H98: L11 | I98: 2002 | K98: =IF(I98="","",YEAR(TODAY())-I98) -> 24 | M98: RGE | N98: =IF(I98>2008,"Evaluation interne", " ") | O98: =IF(I98>2008, I98+20, " ") | P98: N | Q98: =I98+39 -> 2041 | R98: 40000 | AJ98: 170000 | BJ98: Pont 32/32 T SEVAL L11 | BM98: 2029
A99: 2-ESPAGNE | B99: VLL | C99: Pont 32/32 T SEVAL Matricea 13a | D99: Elingue | H99: MAINTENANCE | I99: 2003 | K99: =IF(I99="","",YEAR(TODAY())-I99) -> 23 | M99: RGE | N99: =IF(I99>2008,"Evaluation interne", " ") | O99: =IF(I99>2008, I99+20, " ") | P99: N | Q99: =I99+39 -> 2042 | R99: 40000 | AM99: 170000 | BJ99: Pont 32/32 T SEVAL Matricea 13a | BM99: 2030
A100: 2-ESPAGNE | B100: VLL | C100: Pont 63/63 T SEVAL L13b | D100: Elingue | E100: EGT | H100: L13B | I100: 2003 | K100: =IF(I100="","",YEAR(TODAY())-I100) -> 23 | M100: RGE | N100: =IF(I100>2008,"Evaluation interne", " ") | O100: =IF(I100>2008, I100+20, " ") | P100: N | Q100: =I100+39 -> 2042 | R100: 40000 | AM100: 170000 | BJ100: Pont 63/63 T SEVAL L13b | BM100: 2030
A101: 2-ESPAGNE | B101: VLL | C101: Pont 63/63 T SEVAL L15 | D101: Elingue | E101: EGT | H101: L15 | I101: 2002 | K101: =IF(I101="","",YEAR(TODAY())-I101) -> 24 | M101: RGE | N101: =IF(I101>2008,"Evaluation interne", " ") | O101: =IF(I101>2008, I101+20, " ") | P101: N | Q101: =I101+39 -> 2041 | R101: 40000 | AJ101: 170000 | BJ101: Pont 63/63 T SEVAL L15 | BM101: 2029
...

Sheet TCD12022026
A3: Site | B3: Somme de 2026 OPEX DF (EVS et travaux préconisés) | C3: Somme de 2026 RGE/RGM CAPEX IV | D3: Somme de 2026 ACHAT NEUF CAPEX IV | E3: Somme de 2027 OPEX DF (EVS et travaux préconisés) | F3: Somme de 2027 RGE/RGM CAPEX IV | G3: Somme de 2027 ACHAT NEUF CAPEX IV | H3: Somme de 2028 OPEX DF (EVS et travaux préconisés) | I3: Somme de 2028 ACHAT NEUF CAPEX IV | J3: Somme de 2028 RGE/RGM CAPEX IV | K3: Somme de 2029 OPEX DF (EVS et travaux préconisés) | L3: Somme de 2029 RGE/RGM CAPEX IV | M3: Somme de 2029 ACHAT NEUF CAPEX IV | N3: Somme de 2030 OPEX DF (EVS et travaux préconisés) | O3: Somme de 2030 RGE/RGM CAPEX IV | P3: Somme de 2030 ACHAT NEUF CAPEX IV | Q3: Somme de 2031 OPEX DF (EVS et travaux préconisés) | R3: Somme de 2031 RGE/RGM CAPEX IV | S3: Somme de 2031 ACHAT NEUF CAPEX IV
A4: Bursa | F4: 160000 | O4: 510000 | R4: 170000
A5: Busan
A6: Chassis | C6: 420000 | F6: 340000 | H6: 70000 | K6: 40000
A7: CHENNAI
A8: Cordoba | B8: 39000
A9: Curitiba | F9: 600000 | R9: 300000
A10: LHA | B10: 109000 | C10: 85000 | F10: 340000 | H10: 60000 | I10: 1170000 | R10: 170000
A11: Matrite | H11: 40000
A12: MCA | D12: 290000 | F12: 340000 | J12: 310000 | L12: 170000
A13: PAL | C13: 329000 | E13: 120000 | L13: 170000 | O13: 340000
A14: PITESTI | E14: 15000 | F14: 90000 | H14: 15000 | Q14: 5000
A15: REVOZ | B15: 50000 | D15: 450000 | F15: 50000 | L15: 170000 | O15: 170000 | R15: 170000
A16: Tanger | B16: 65000 | E16: 65000 | G16: 1375000 | H16: 65000 | K16: 65000 | N16: 65000
A17: UGB | B17: 280000 | E17: 40000 | F17: 680000 | I17: 1700000 | J17: 340000 | L17: 340000 | N17: 40000 | O17: 170000 | R17: 170000
A18: UPL | B18: 113600 | E18: 117000 | F18: 230000 | G18: 860000 | H18: 8600 | I18: 860000 | J18: 170000 | N18: 48000 | O18: 340000 | S18: 850000
A19: VLL | F19: 490000 | J19: 340000 | L19: 340000 | O19: 340000 | R19: 340000
A20: Total général | B20: 656600 | C20: 834000 | D20: 740000 | E20: 357000 | F20: 3320000 | G20: 2235000 | H20: 258600 | I20: 3730000 | J20: 1160000 | K20: 105000 | L20: 1190000 | N20: 153000 | O20: 1870000 | Q20: 5000 | R20: 1320000 | S20: 850000

Sheet EVENT GATES
A2: Somme de EGT € | D2: EGT
A3: PAYS | B3: Site | C3: Pont | D3: 2025 | E3: 2026 | F3: 2027 | G3: 2028
A4: 1-FRANCE | B4: LHA | C4: J2 Nord | F4: 80000
C5: J2 Sud | E5: 80000
B6: MCA | C6: Pont 25/25 T Sud SEVAL L01 | F6: 80000
B7: UGB | C7: Pont A12 Caillard/SAMETO 63 T | E7: 80000
B8: UPL | C8: Pont AA5 28 T SEVAL | F8: 80000
A9: 2-ESPAGNE | B9: PAL | C9: Pont 45/45T PG7 GH | F9: 83000
B10: VLL | C10: Pont 32/32 T SEVAL L5 | E10: 88000
A11: COREE | B11: Busan | C11: Pont 3-2 40 T pour presse 5100 T
A12: INDE | B12: CHENNAI | C12: Pont N°6 40T DEMAG | F12: 55000
C13: Pont N°8 40 T DEMAG | F13: 55000
A14: MAROC | B14: Tanger | C14: Pont 52 32 T ADC | F14: 66000
C15: Pont 607 32 T KONECRANES | E15: 66000
A16: ROUMANIE | B16: PITESTI | C16: Pont 14 TGSE 50 T PROMPT | E16: 65000
C17: Pont 16 HS 50/25 T ADC | F17: 65000
C18: Pont 5 32/8T PROMPT | E18: 65000
A19: TURQUIE | B19: Bursa | C19: Pont 45/45 T XLHS GMT | D19: 55000
C20: Pont 50/20 T TGP 100 GMT | F20: 55000
C21: Pont XL HS GMT | E21: 55000
A22: Total général | D22: 55000 | E22: 499000 | F22: 619000
D29: =COUNTA(D4:D22) -> 2 | E29: =COUNTA(E4:E22) -> 8 | F29: =COUNTA(F4:F21) -> 9

Sheet Règles
A1: Règles | B1: Date | C1: commentaires
A2: Règle | B2: 45471 | C2: J’ai mis 39 ans pour l’EVS après la date du PONT. 40k€ pour PONT et 25k€ pour SP.
B3: 45471 | C3: 1. Il manque le PONT BURSA XL de 2025 ? Pont 45/45 T XLHS GMT ?
B4: 45471 | C4: 2. Les petites RGE sont changement de variateurs et chemin de roulement.
B5: 45471 | C5: 3. J’ai mis en rouge les gros montants qu’on avait déjà identifié dans la base. Les gros montants c’est au cas où l’EVS est négatif.
B6: 45477 | C6: 4. A compléter les montants de RGE ? Fait en jaune pour approx
A7: Règle | B7: 45471 | C7: Prolongation possible après EVS positif => 3 ans en général au mieux 5/10 ans et au pire 12 mois
A8: Règle | B8: 45471 | C8: 40 ans théorique - Au bout de 39 ans , vérifier l'EVS. Pont ADC +19 ans et PONT KONECRANE +39 ans
A9: Règle | B9: 45471 | C9: RG ISCIR - Règlement spéciale Roumanie tous les 15 ans

Sheet CPI SAP
A1: Site | B1: Project | C1: Project name | D1: CATEGORIE | E1: 2025 | F1: Budget 25 | G1: 2024 | H1: 2026 | I1: 2027 | J1: 2028
A2: CURITIBA USINE A.SENNA | B2: EHI287600 | C2: Pont Roulant 1 TGSE 1 | D2: PONT | E2: 0,00 | F2: 0,00 | G2: 0 | H2: 400 000 € | I2: 0 | J2: 0
A3: CURITIBA USINE A.SENNA | B3: EHI287700 | C3: Pont Roulant 1 TGSE 2 | D3: PONT | E3: 0,00 | F3: 0,00 | G3: 0 | H3: 400 000 € | I3: 0 | J3: 0
A4: TANGER | B4: EII072000 | C4: PONT EMBOUTISSAGE | D4: PONT | E4: 0,00 | F4: 0,00 | G4: 0 | H4: 400 000 € | I4: 0 | J4: 0
A5: BURSA | B5: EGI075700 | C5: PONT XL + TRANSBORDEUR BURSA | D5: CAPACITAIRE | E5: 1 574 000,00 | F5: 1 440 000,00 | G5: 60 000 € | H5: 0 | I5: 0 | J5: 0
A6: MIOVENI (DACIA) | B6: EII063800 | C6: Pont roulant 15 HS PITESTI | D6: PONT | E6: 0,00 | F6: 0,00 | G6: 75 000 € | H6: 0 | I6: 0 | J6: 0
A7: DOUAI | B7: EHI153200 | C7: L21 UGB remplacement pont A12 | D7: PONT | E7: 0,00 | F7: 0,00 | G7: 0 | H7: 0 | I7: 0 | J7: 900 000 €
A8: DOUAI | B8: EHI153500 | C8: UGB remplacement pont A18 | D8: PONT | E8: 0,00 | F8: 0,00 | G8: 0 | H8: 800 000 € | I8: 0 | J8: 0
A9: FLINS | B9: EHI154900 | C9: UPL Pont L62 Poutres AB6+ RG Pinces | D9: PONT | E9: 0,00 | F9: 0,00 | G9: 0 | H9: 1 | I9: 0 | J9: 0
A10: FLINS | B10: EHI155000 | C10: UPL remplacement Ponts RA Sud + RGE AB5 | D10: PONT | E10: 0,00 | F10: 0,00 | G10: 0 | H10: 850 000 € | I10: 0 | J10: 0
A11: FLINS | B11: EHI155100 | C11: UPL rplct Pont RA Centre RGE Ponts AB1 2 | D11: PONT | E11: 0,00 | F11: 0,00 | G11: 0 | H11: 860 000 € | I11: 0 | J11: 0
A12: MAUBEUGE | B12: EHI153600 | C12: MCA RGE PONT 25T PAL (zone PAL )​ | D12: PONT | E12: 135 000,00 | F12: 0,00 | G12: 0 | H12: 0 | I12: 0 | J12: 0
A13: MAUBEUGE | B13: EHI153700 | C13: MCA RGE SP25T + Pont 80 T | D13: PONT | E13: 0,00 | F13: 0,00 | G13: 0 | H13: 300 000 € | I13: 0 | J13: 0
A14: MAUBEUGE | B14: EII143100 | C14: MCA RGE PONT 25T Nord | D14: PONT | E14: 0,00 | F14: 0,00 | G14: 0 | H14: 155 000 € | I14: 0 | J14: 0
A15: NOVO MESTO | B15: EEI223300 | C15: REV RG PONT N°4 Travée MAP | D15: PONT | E15: 400 000,00 | F15: 0,00 | G15: 0 | H15: 0 | I15: 0 | J15: 0
A16: PALENCIA | B16: EDI286300 | C16: L5 PAL AUGMENTATION CAPA ALU - 2ème PONT | D16: CAPACITAIRE LIE | E16: 0,00 | F16: 0,00 | G16: 0 | H16: 0 | I16: 0 | J16: 0
A17: DOUAI | B17: EHI153400 | C17: UGB Remplacement PONT SP A16 | D17: PONT | H17: 250 000 €
A18: MAUBEUGE | B18: EHI153800 | C18: MCA RGE 25T sud + 32T bobines | D18: PONT | H18: 290 000€
A19: SANDOUVILLE | B19: EHI154500 | C19: LHA anti crabe J11 + RG Pince J11 | D19: PONT | E19: 200 000€
A20: SANDOUVILLE | B20: EHI154600 | C20: LHA Remplacement J1 Sud + RG voie de rlt | D20: PONT | H20: 1 120 000€
A21: SANDOUVILLE | B21: EHI154700 | C21: LHA Remplacement J3 + remplacement rails | D21: PONT | H21: 1 170 000€
A22: PROVISIONS
A23: RSAS | B23: AAI823300 | C23: PROVISION SECURISATION MOYENS LEVAGE | D23: PONT | H23: 1000000
A24: TANGER | B24: EII072000 | C24: PONT | D24: PONT | H24: 400000
A25: NOVO MESTO | B25: EHI251500 | C25: REV RGM Moyens de Levage | D25: PONT | H25: 300000

Sheet SAUVPonts FEV26
C2: A consolider | V2: A consolider
C3: EVS passée | V3: EVS passée
C4: En cas D'EVS négatif (changement pont) | V4: En cas D'EVS négatif (changement pont)
C5: Travaux spécifiques | V5: Travaux spécifiques
C6: RGE 25 ans | V6: RGE 25 ans
C7: RGE 50 ans | V7: RGE 50 ans
C8: EVS + tx suite EVS (réparation type soudures) | V8: EVS + tx suite EVS (réparation type soudures)
B9: En Euros | K9: NEW ! | L9: NEW ! | M9: Evaluation Speciale | P9: OPEX usine = EVS + RGM après EVS + RGE après EVS (RGE "50 ans") CAPEX = RGE 25 ans + Installation nouveaux ponts (si EVS négatif) | BJ9: =COUNTA(BJ11:BJ181) -> 151 | BK9: ROADMAP SECURISATION DES PONTS
A10: PAYS | B10: Site | C10: Pont | D10: ACCESSOIRES : Pince ou Elingue | E10: Ligne de Presse ou utilisation | F10: MES | G10: Observations | H10: Age | I10: PRIX NEUF | J10: Travaux RG ou Installation Nouveau Pont | K10: Pont à évaluer en interne par Référent Levage (MES>2008) | L10: Année Evaluation Interne | M10: Evaluation Spéciale O/N | N10: EVS Année | O10: E/S Montant | P10: 2024 | Q10: 2025 OPEX DF (EVS et travaux préconisés) (EVS et travaux préconisés) | R10: 2025 RGE/RGM CAPEX IV | S10: 2025 ACHAT NEUF CAPEX IV | T10: 2026 OPEX DF (EVS et travaux préconisés) | U10: 2026 RGE/RGM CAPEX IV | V10: 2026 ACHAT NEUF CAPEX IV | W10: 2027 OPEX DF (EVS et travaux préconisés) | X10: 2027 RGE/RGM CAPEX IV | Y10: 2027 ACHAT NEUF CAPEX IV | Z10: 2028 OPEX DF (EVS et travaux préconisés) | AA10: 2028 RGE/RGM CAPEX IV | AB10: 2028 ACHAT NEUF CAPEX IV | AC10: 2029 OPEX DF (EVS et travaux préconisés) | AD10: 2029 RGE/RGM CAPEX IV | AE10: 2029 ACHAT NEUF CAPEX IV | AF10: 2030 OPEX DF (EVS et travaux préconisés) | AG10: 2030 RGE/RGM CAPEX IV | AH10: 2030 ACHAT NEUF CAPEX IV | AI10: 2031 OPEX DF (EVS et travaux préconisés) | AJ10: 2031 RGE/RGM CAPEX IV | AK10: 2031 ACHAT NEUF CAPEX IV | AL10: 2032 OPEX DF (EVS et travaux préconisés) | AM10: 2032 RGE/RGM CAPEX IV | AN10: 2032 ACHAT NEUF CAPEX IV | AO10: 2033 OPEX DF (EVS et travaux préconisés) | AP10: 2033 RGE/RGM CAPEX IV | AQ10: 2033 ACHAT NEUF CAPEX IV | AR10: 2034 OPEX DF (EVS et travaux préconisés) | AS10: 2034 RGE/RGM CAPEX IV | AT10: 2034 ACHAT NEUF CAPEX IV | AU10: 2035 OPEX DF (EVS et travaux préconisés) | AV10: 2035 RGE/RGM CAPEX IV | AW10: 2035 ACHAT NEUF CAPEX IV | AX10: 2036 OPEX DF (EVS et travaux préconisés) | AY10: 2036 RGE/RGM CAPEX IV | AZ10: 2036 ACHAT NEUF CAPEX IV | BA10: 2037 OPEX DF (EVS et travaux préconisés) | BB10: 2037 RGE/RGM CAPEX IV | BC10: 2037 ACHAT NEUF CAPEX IV | BD10: EGT | BE10: COMMENTAIRES ER SUIVI BAI | BK10: USAGE : Manutention et/ou Manipulation | BL10: TYPE : Automate ou Electromécanique | BM10: ROADMAP Capex Obsolescence | BN10: ROADMAP SECURISATION
A11: 1-FRANCE | B11: Chassis | C11: Pont E4 20T 48444 SEVAL/OMIS | F11: 2012 | G11: HORS SCOPE DEPT EMB | H11: =IF(F11="","",YEAR(TODAY())-F11) -> 14 | K11: =IF(F11>2008,"Evaluation interne", " ") -> Evaluation interne | L11: =IF(F11>2008, F11+20, " ") -> 2032 | M11: N | N11: =F11+39 -> 2051 | O11: 40000 | BJ11: Pont E4 20T 48444 SEVAL/OMIS
A12: 1-FRANCE | B12: Chassis | C12: Pont E0 46833 25 T KONECRANES | F12: 2010 | G12: HORS SCOPE DEPT EMB | H12: =IF(F12="","",YEAR(TODAY())-F12) -> 16 | J12: RGE | K12: =IF(F12>2008,"Evaluation interne", " ") -> Evaluation interne | L12: =IF(F12>2008, F12+20, " ") -> 2030 | M12: N | N12: =F12+39 -> 2049 | O12: 40000 | AU12: 40000 | BJ12: Pont E0 46833 25 T KONECRANES | BM12: 2035
A13: 1-FRANCE | B13: Chassis | C13: SP HH3 44839 25T ADC | F13: 2008 | G13: HORS SCOPE DEPT EMB | H13: =IF(F13="","",YEAR(TODAY())-F13) -> 18 | J13: RGE | K13: =IF(F13>2008,"Evaluation interne", " ") | L13: =IF(F13>2008, F13+20, " ") | M13: N | N13: =F13+39 -> 2047 | O13: 25000 | AO13: 50000 | BJ13: SP HH3 44839 25T ADC | BK13: Manipulation | BM13: 2033
A14: 1-FRANCE | B14: Chassis | C14: Pont E2 1470200822 4T SEVAL | F14: 2003 | G14: HORS SCOPE DEPT EMB | H14: =IF(F14="","",YEAR(TODAY())-F14) -> 23 | K14: =IF(F14>2008,"Evaluation interne", " ") | L14: =IF(F14>2008, F14+20, " ") | M14: N | N14: =F14+39 -> 2042 | O14: 40000 | BJ14: Pont E2 1470200822 4T SEVAL
A15: 1-FRANCE | B15: Chassis | C15: Pont E2' 1470200821 8/8 T DEMAG | F15: 2003 | G15: HORS SCOPE DEPT EMB | H15: =IF(F15="","",YEAR(TODAY())-F15) -> 23 | K15: =IF(F15>2008,"Evaluation interne", " ") | L15: =IF(F15>2008, F15+20, " ") | M15: N | N15: =F15+39 -> 2042 | O15: 40000 | BJ15: Pont E2' 1470200821 8/8 T DEMAG
A16: 1-FRANCE | B16: Chassis | C16: Pont E2 1470200820 14/14 T SEVAL | F16: 2003 | G16: HORS SCOPE DEPT EMB | H16: =IF(F16="","",YEAR(TODAY())-F16) -> 23 | J16: RGE | K16: =IF(F16>2008,"Evaluation interne", " ") | L16: =IF(F16>2008, F16+20, " ") | M16: N | N16: =F16+39 -> 2042 | O16: 40000 | AC16: 40000 | BJ16: Pont E2 1470200820 14/14 T SEVAL | BM16: 2029
A17: 1-FRANCE | B17: Chassis | C17: Pont (SP ?) E4 1470200756 8T | F17: 2003 | G17: HORS SCOPE DEPT EMB | H17: =IF(F17="","",YEAR(TODAY())-F17) -> 23 | J17: RGE | K17: =IF(F17>2008,"Evaluation interne", " ") | L17: =IF(F17>2008, F17+20, " ") | M17: N | N17: =F17+39 -> 2042 | O17: 40000 | Z17: 20000 | BJ17: Pont (SP ?) E4 1470200756 8T | BM17: 2028
A18: 1-FRANCE | B18: Chassis | C18: Pont E5 25 T 1470200554 SEVAL | F18: 2003 | G18: HORS SCOPE DEPT EMB | H18: =IF(F18="","",YEAR(TODAY())-F18) -> 23 | J18: RGE | K18: =IF(F18>2008,"Evaluation interne", " ") | L18: =IF(F18>2008, F18+20, " ") | M18: N | N18: =F18+39 -> 2042 | O18: 40000 | Z18: 50000 | BJ18: Pont E5 25 T 1470200554 SEVAL | BM18: 2028
A19: 1-FRANCE | B19: Chassis | C19: Pont E6 1470000240 50T SAMETO | F19: 2001 | G19: HORS SCOPE DEPT EMB | H19: =IF(F19="","",YEAR(TODAY())-F19) -> 25 | J19: RGE 25 ans | K19: =IF(F19>2008,"Evaluation interne", " ") | L19: =IF(F19>2008, F19+20, " ") | M19: N | N19: =F19+39 -> 2040 | O19: 40000 | X19: 170000 | BJ19: Pont E6 1470000240 50T SAMETO | BM19: 2027 | BN19: 2025
A20: 1-FRANCE | B20: Chassis | C20: Pont E6 1470001297 50/50T SAMETO | F20: 2001 | G20: HORS SCOPE DEPT EMB | H20: =IF(F20="","",YEAR(TODAY())-F20) -> 25 | J20: RGE 25 ans | K20: =IF(F20>2008,"Evaluation interne", " ") | L20: =IF(F20>2008, F20+20, " ") | M20: N | N20: =F20+39 -> 2040 | O20: 40000 | X20: 170000 | BJ20: Pont E6 1470001297 50/50T SAMETO | BM20: 2027
A21: 1-FRANCE | B21: Chassis | C21: Pont E0 1470000704 25 T SEVAL | F21: 2000 | G21: HORS SCOPE DEPT EMB | H21: =IF(F21="","",YEAR(TODAY())-F21) -> 26 | J21: RGE | K21: =IF(F21>2008,"Evaluation interne", " ") | L21: =IF(F21>2008, F21+20, " ") | M21: N | N21: =F21+39 -> 2039 | O21: 40000 | U21: 150000 | BJ21: Pont E0 1470000704 25 T SEVAL | BM21: 2026
A22: 1-FRANCE | B22: Chassis | C22: Pont E2 1479900509 16T SAMETO | F22: 1999 | G22: HORS SCOPE DEPT EMB | H22: =IF(F22="","",YEAR(TODAY())-F22) -> 27 | J22: RGE | K22: =IF(F22>2008,"Evaluation interne", " ") | L22: =IF(F22>2008, F22+20, " ") | M22: N | N22: =F22+39 -> 2038 | O22: 40000 | U22: 120000 | BJ22: Pont E2 1479900509 16T SAMETO | BM22: 2026
A23: 1-FRANCE | B23: Chassis | C23: Pont E1 759847 20T SAMETO | F23: 1994 | G23: HORS SCOPE DEPT EMB | H23: =IF(F23="","",YEAR(TODAY())-F23) -> 32 | J23: RGE | K23: =IF(F23>2008,"Evaluation interne", " ") | L23: =IF(F23>2008, F23+20, " ") | M23: N | N23: =F23+39 -> 2033 | O23: 40000 | U23: 150000 | BJ23: Pont E1 759847 20T SAMETO | BM23: 2026
A24: 1-FRANCE | B24: Chassis | C24: Pont E1 759848 20/20 T SAMETO (RGE 2019) | F24: 1994 | G24: HORS SCOPE DEPT EMB | H24: =IF(F24="","",YEAR(TODAY())-F24) -> 32 | K24: =IF(F24>2008,"Evaluation interne", " ") | L24: =IF(F24>2008, F24+20, " ") | M24: N | N24: =F24+39 -> 2033 | O24: 40000 | BJ24: Pont E1 759848 20/20 T SAMETO (RGE 2019)
A25: 1-FRANCE | B25: LHA | C25: Pont J12 63T | D25: Pince | E25: L08 | F25: 2006 | H25: =IF(F25="","",YEAR(TODAY())-F25) -> 20 | I25: ='DEMARCHE EVS'!B9 -> 950000 | J25: RGE | K25: =IF(F25>2008,"Evaluation interne", " ") | L25: =IF(F25>2008, F25+20, " ") | M25: NC | N25: =F25+39 -> 2045 | O25: 40000 | Z25: 60000 | BJ25: Pont J12 | BM25: 2028
A26: 1-FRANCE | B26: LHA | C26: Pont J11 63T | D26: Pince | E26: L11 | F26: 2006 | H26: =IF(F26="","",YEAR(TODAY())-F26) -> 20 | J26: RGE | K26: =IF(F26>2008,"Evaluation interne", " ") | L26: =IF(F26>2008, F26+20, " ") | N26: =F26+39 -> 2045 | O26: 40000 | AJ26: 170000 | BJ26: Pont J11 | BM26: 2029
A27: 1-FRANCE | B27: LHA | C27: Pince outils J11 | D27: PINCE | E27: L11 | F27: 1999 | H27: =IF(F27="","",YEAR(TODAY())-F27) -> 27 | J27: RG | K27: =IF(F27>2008,"Evaluation interne", " ") | L27: =IF(F27>2008, F27+20, " ") | M27: NC | R27: 100000
A28: 1-FRANCE | B28: LHA | C28: Pince à outil J12 | D28: PINCE | E28: STOCKAGE | F28: 1999 | H28: =IF(F28="","",YEAR(TODAY())-F28) -> 27 | I28: 220000 | J28: RGM | K28: =IF(F28>2008,"Evaluation interne", " ") | L28: =IF(F28>2008, F28+20, " ") | M28: NC | U28: 85000
A29: 1-FRANCE | B29: LHA | C29: Semi-portique N°1 J3 CHSL | E29: n fc | F29: 1979 | H29: =IF(F29="","",YEAR(TODAY())-F29) -> 47 | I29: 120000 | J29: RG | K29: =IF(F29>2008,"Evaluation interne", " ") | L29: =IF(F29>2008, F29+20, " ") | M29: N | N29: 2026 | O29: 20000 | T29: 20000 | BJ29: Semi-portique N°1 J3 CHSL | BK29: Manipulation
A30: 1-FRANCE | B30: LHA | C30: Semi-portique N°2 J3 CHSL (10T SAMETO?)-STOP 06/02 | E30: MAP/MAINTENANCE | F30: 1979 | H30: =IF(F30="","",YEAR(TODAY())-F30) -> 47 | I30: 120000 | J30: RG | K30: =IF(F30>2008,"Evaluation interne", " ") | L30: =IF(F30>2008, F30+20, " ") | M30: N | N30: 2026 | O30: 20000 | T30: =20000 -> 20000 | BJ30: Semi-portqiue N°2 J3 CHSL | BK30: Manipulation
A31: 1-FRANCE | B31: LHA | C31: Pont J1sud 63T | E31: 80%OUTILS / 20%BOBINES | F31: 1970 | H31: =IF(F31="","",YEAR(TODAY())-F31) -> 56 | J31: RGE 50 ans | K31: =IF(F31>2008,"Evaluation interne", " ") | L31: =IF(F31>2008, F31+20, " ") | M31: O | N31: 2035 | O31: 40000 | Q31: =40000 + 25000 -> 65000 | X31: 170000 | AU31: 40000 | AW31: 1120000 | BJ31: Pont J1sud 63T | BM31: 2026
A32: 1-FRANCE | B32: LHA | C32: Pont J3 63/63T CAILLARD | E32: MAP/MAINTENANCE | F32: 1970 | H32: =IF(F32="","",YEAR(TODAY())-F32) -> 56 | I32: 1170000 | J32: 2026 prov pour travaux / Installation nouveaux ponts 2027 | K32: =IF(F32>2008,"Evaluation interne", " ") | L32: =IF(F32>2008, F32+20, " ") | M32: N | N32: 2026 | O32: 40000 | T32: 69000 | X32: 170000 | AB32: 1170000 | BJ32: Pont J3 63/63T CAILLARD | BM32: 2026
A33: 1-FRANCE | B33: LHA | C33: Chemins de roulement J3 | E33: MAP/MAINTENANCE | F33: 1970 | H33: =IF(F33="","",YEAR(TODAY())-F33) -> 56 | I33: nc | J33: RG | K33: =IF(F33>2008,"Evaluation interne", " ") | L33: =IF(F33>2008, F33+20, " ") | M33: NC | BJ33: Chemins de roulement J3
A34: 1-FRANCE | B34: LHA | C34: Chemins de roulement J1 SUD 63T, soudures | E34: BOBINES | F34: 1970 | H34: =IF(F34="","",YEAR(TODAY())-F34) -> 56 | I34: nc | J34: RG | K34: =IF(F34>2008,"Evaluation interne", " ") | L34: =IF(F34>2008, F34+20, " ") | M34: NC | BJ34: Chemins de roulement J1, soudures
A35: 1-FRANCE | B35: LHA | C35: J1 Nord | D35: Pince | E35: STOCKAGE | H35: =IF(F35="","",YEAR(TODAY())-F35) | K35: =IF(F35>2008,"Evaluation interne", " ") | L35: =IF(F35>2008, F35+20, " ") | BJ35: J1 Nord
A36: 1-FRANCE | B36: LHA | C36: J2 Nord | D36: Elingue | E36: STOCKAGE | H36: =IF(F36="","",YEAR(TODAY())-F36) | K36: =IF(F36>2008,"Evaluation interne", " ") | L36: =IF(F36>2008, F36+20, " ") | BD36: EGT | BJ36: J2 Nord | BN36: 2025
A37: 1-FRANCE | B37: LHA | C37: J2 Sud | D37: Elingue | E37: PAL/PAVAR | H37: =IF(F37="","",YEAR(TODAY())-F37) | K37: =IF(F37>2008,"Evaluation interne", " ") | L37: =IF(F37>2008, F37+20, " ") | BD37: 2026 | BJ37: J2 Sud
A38: 1-FRANCE | B38: MCA | C38: Pont 63T XLHS SECAL | D38: Pince | E38: XL HS | F38: 2019 | H38: =IF(F38="","",YEAR(TODAY())-F38) -> 7 | K38: =IF(F38>2008,"Evaluation interne", " ") -> Evaluation interne | L38: =IF(F38>2008, F38+20, " ") -> 2039 | M38: N | N38: =F38+20 -> 2039 | O38: 40000 | AA38: 140000 | BJ38: Pont 63T XLHS SECAL | BM38: 2028
A39: 1-FRANCE | B39: MCA | C39: PINCE 50T XXL HS | E39: XXL HS | F39: 2019 | H39: =IF(F39="","",YEAR(TODAY())-F39) -> 7 | K39: =IF(F39>2008,"Evaluation interne", " ") -> Evaluation interne | L39: =IF(F39>2008, F39+20, " ") -> 2039 | N39: 2039
A40: 1-FRANCE | B40: MCA | C40: Pont 50/50 T XLHS SECAL | D40: Pince | E40: MAP XL | F40: 2019 | H40: =IF(F40="","",YEAR(TODAY())-F40) -> 7 | K40: =IF(F40>2008,"Evaluation interne", " ") -> Evaluation interne | L40: =IF(F40>2008, F40+20, " ") -> 2039 | M40: N | N40: =F40+39 -> 2058 | O40: 40000 | AD40: 170000 | BJ40: Pont 50/50 T XLHS SECAL | BM40: 2029
A41: 1-FRANCE | B41: MCA | C41: Pont 25 T PAL SEVAL | D41: Elingue | E41: PAL | F41: 2001 | H41: =IF(F41="","",YEAR(TODAY())-F41) -> 25 | J41: RGE 25 ans | K41: =IF(F41>2008,"Evaluation interne", " ") | L41: =IF(F41>2008, F41+20, " ") | M41: N | N41: =F41+39 -> 2040 | O41: 40000 | R41: 135000 | V41: 290000 | BD41: EGT | BJ41: Pont 25 T PAL SEVAL | BM41: 2025
A42: 1-FRANCE | B42: MCA | C42: Pont 32 T Appro bobines SAMETO | D42: Pince | E42: BOBINES | F42: 2000 | H42: =IF(F42="","",YEAR(TODAY())-F42) -> 26 | J42: RGE 25 ans | K42: =IF(F42>2008,"Evaluation interne", " ") | L42: =IF(F42>2008, F42+20, " ") | M42: N | N42: =F42+39 -> 2039 | O42: 40000 | AA42: 170000 | BJ42: Pont 32 T Appro bobines SAMETO | BM42: 2027
A43: 1-FRANCE | B43: MCA | C43: Pont 25/25T Nord SAMETO | D43: Elingue | E43: MAP (et ex L3) | F43: 1998 | H43: =IF(F43="","",YEAR(TODAY())-F43) -> 28 | J43: RGE 25 ans | K43: =IF(F43>2008,"Evaluation interne", " ") | L43: =IF(F43>2008, F43+20, " ") | M43: N | N43: =F43+39 -> 2037 | O43: 40000 | X43: 0 | BJ43: Pont 25/25T Nord SAMETO | BM43: 2025 | BN43: 2025
A44: 1-FRANCE | B44: MCA | C44: Semi-portique 25/25 T surclassé 30T SEVAL | E44: MAP/travée 5400T | F44: 1996 | H44: =IF(F44="","",YEAR(TODAY())-F44) -> 30 | J44: RGE 25 ans | K44: =IF(F44>2008,"Evaluation interne", " ") | L44: =IF(F44>2008, F44+20, " ") | M44: N | N44: 2035 | O44: 25000 | X44: 170000 | BJ44: Semi-portique 25/25 T surclassé 30T SEVAL | BM44: 2026
A45: 1-FRANCE | B45: MCA | C45: Pont 80T SAMETO | D45: Pince | E45: PT5400 | F45: 1995 | H45: =IF(F45="","",YEAR(TODAY())-F45) -> 31 | J45: RGE 25 ans | K45: =IF(F45>2008,"Evaluation interne", " ") | L45: =IF(F45>2008, F45+20, " ") | M45: N | N45: 2034 | O45: 40000 | X45: 0 | BJ45: Pont 80T SAMETO | BM45: 2026
A46: 1-FRANCE | B46: MCA | C46: Pont 25/25 T Sud SEVAL L01 | D46: Elingue | E46: L01 | F46: 1994 | H46: =IF(F46="","",YEAR(TODAY())-F46) -> 32 | J46: RGE 25 ans | K46: =IF(F46>2008,"Evaluation interne", " ") | L46: =IF(F46>2008, F46+20, " ") | M46: N | N46: 2033 | O46: 40000 | X46: 170000 | BD46: 2026B | BE46: 170000 | BJ46: Pont 25/25 T Sud SEVAL | BM46: 2027
A47: 1-FRANCE | B47: UGB | C47: Pont A1 GE 35 T SECAL | D47: Pince | E47: BOBINES | F47: 2016 | H47: =IF(F47="","",YEAR(TODAY())-F47) -> 10 | K47: =IF(F47>2008,"Evaluation interne", " ") -> Evaluation interne | L47: =IF(F47>2008, F47+20, " ") -> 2036 | M47: N | N47: =F47+39 -> 2055 | O47: 40000 | BJ47: Pont A1 GE 35 T SECAL | BM47: Pince
A48: 1-FRANCE | B48: UGB | C48: Pont A13 80 T SECAL/OMIS | D48: Pince | E48: PT5400 | F48: 2015 | H48: =IF(F48="","",YEAR(TODAY())-F48) -> 11 | K48: =IF(F48>2008,"Evaluation interne", " ") -> Evaluation interne | L48: =IF(F48>2008, F48+20, " ") -> 2035 | M48: N | N48: =F48+39 -> 2054 | O48: 40000 | BJ48: Pont A13 80 T SECAL/OMIS
A49: 1-FRANCE | B49: UGB | C49: Pont A15 50/50 T SEVAL/OMIS | E49: X | F49: 2012 | H49: =IF(F49="","",YEAR(TODAY())-F49) -> 14 | K49: =IF(F49>2008,"Evaluation interne", " ") -> Evaluation interne | L49: =IF(F49>2008, F49+20, " ") -> 2032 | M49: N | N49: =F49+39 -> 2051 | O49: 40000 | BD49: EGT | BJ49: Pont A15 50/50 T SEVAL/OMIS
A50: 1-FRANCE | B50: UGB | C50: Pont A1 PE 35 T KONECRANES | D50: Pince | E50: BOBINES | F50: 2010 | H50: =IF(F50="","",YEAR(TODAY())-F50) -> 16 | J50: RGE 25 ans | K50: =IF(F50>2008,"Evaluation interne", " ") -> Evaluation interne | L50: =IF(F50>2008, F50+20, " ") -> 2030 | M50: N | N50: =F50+39 -> 2049 | O50: 40000 | AF50: 40000 | AV50: 170000 | BJ50: Pont A1 PE 35 T KONECRANES | BM50: 2035
A51: 1-FRANCE | B51: UGB | C51: Pont A17 35 T SEVAL/OMIS | E51: INJECTION | F51: 2009 | H51: =IF(F51="","",YEAR(TODAY())-F51) -> 17 | K51: =IF(F51>2008,"Evaluation interne", " ") -> Evaluation interne | L51: =IF(F51>2008, F51+20, " ") -> 2029 | M51: N | N51: =F51+39 -> 2048 | O51: 40000 | BJ51: Pont A17 35 T SEVAL/OMIS
A52: 1-FRANCE | B52: UGB | C52: Pont A2 GE 35 T KONECRANES | D52: Elingue | E52: DECOUPES | F52: 2008 | H52: =IF(F52="","",YEAR(TODAY())-F52) -> 18 | J52: RGE 25 ans | K52: =IF(F52>2008,"Evaluation interne", " ") | L52: =IF(F52>2008, F52+20, " ") | M52: N | N52: =F52+39 -> 2047 | O52: 40000 | AP52: 170000 | BD52: EGT | BJ52: Pont A2 GE 35 T KONECRANES | BM52: 2033
A53: 1-FRANCE | B53: UGB | C53: Pont A2 PE 35 T KONECRANES | D53: Elingue | E53: DECOUPES | F53: 2006 | H53: =IF(F53="","",YEAR(TODAY())-F53) -> 20 | J53: RGE 25 ans | K53: =IF(F53>2008,"Evaluation interne", " ") | L53: =IF(F53>2008, F53+20, " ") | M53: N | N53: =F53+39 -> 2045 | O53: 40000 | AJ53: 170000 | BD53: EGT | BJ53: Pont A2 PE 35 T KONECRANES | BM53: 2031
A54: 1-FRANCE | B54: UGB | C54: Pont A14 63/63 T ADC | E54: X MP | F54: 2019 | H54: =IF(F54="","",YEAR(TODAY())-F54) -> 7 | K54: =IF(F54>2008,"Evaluation interne", " ") -> Evaluation interne | L54: =IF(F54>2008, F54+20, " ") -> 2039 | M54: N | N54: =F54+39 -> 2058 | O54: 40000 | BD54: EGT | BJ54: Pont A14 63/63 T ADC
A55: 1-FRANCE | B55: UGB | C55: Pont A9 63/63 T KONECRANES | E55: MAINTENANCE/MAP | F55: 2005 | H55: =IF(F55="","",YEAR(TODAY())-F55) -> 21 | J55: RGE 25 ans | K55: =IF(F55>2008,"Evaluation interne", " ") | L55: =IF(F55>2008, F55+20, " ") | M55: N | N55: =F55+39 -> 2044 | O55: 40000 | AG55: 170000 | BJ55: Pont A9 63/63 T KONECRANES | BM55: 2030
A56: 1-FRANCE | B56: UGB | C56: Pont A7 63/63 T SEVAL | D56: Elingue | E56: STOCKAGE | F56: 2004 | H56: =IF(F56="","",YEAR(TODAY())-F56) -> 22 | J56: RGE 25 ans | K56: =IF(F56>2008,"Evaluation interne", " ") | L56: =IF(F56>2008, F56+20, " ") | M56: N | N56: =F56+39 -> 2043 | O56: 40000 | AD56: 170000 | BD56: EGT | BJ56: Pont A7 63/63 T SEVAL | BM56: 2029
A57: 1-FRANCE | B57: UGB | C57: Pont A8 63/63 T SAMETO | D57: Elingue | E57: L12 | F57: 2001 | H57: =IF(F57="","",YEAR(TODAY())-F57) -> 25 | I57: 1170000 | J57: RGE 25 ans | K57: =IF(F57>2008,"Evaluation interne", " ") | L57: =IF(F57>2008, F57+20, " ") | M57: N | N57: =F57+39 -> 2040 | O57: 40000 | X57: 170000 | AD57: 170000 | BD57: EGT | BJ57: Pont A8 63/63 T SAMETO | BM57: 2026 | BN57: 2026 | BO57: était prévu 2025, budget 25 transféré à CVP
A58: 1-FRANCE | B58: UGB | C58: Pont A2 50 T SAMETO | D58: Elingue | E58: DECOUPES | F58: 2001 | G58: AC installé en 2018 suite usure galets | H58: =IF(F58="","",YEAR(TODAY())-F58) -> 25 | J58: RGE 25 ans | K58: =IF(F58>2008,"Evaluation interne", " ") | L58: =IF(F58>2008, F58+20, " ") | M58: N | N58: =F58+39 -> 2040 | O58: 40000 | AA58: 170000 | BD58: EGT | BJ58: Pont A2 50 T SAMETO | BM58: 2027
A59: 1-FRANCE | B59: UGB | C59: Pont A10 63/63 T SAMETO | E59: X L17 | F59: 1996 | H59: =IF(F59="","",YEAR(TODAY())-F59) -> 30 | J59: RGE 25 ans | K59: =IF(F59>2008,"Evaluation interne", " ") | L59: =IF(F59>2008, F59+20, " ") | M59: N | N59: =F59+39 -> 2035 | O59: 40000 | X59: 170000 | BD59: EGT | BJ59: Pont A10 63/63 T SAMETO | BM59: 2027
A60: 1-FRANCE | B60: UGB | C60: Pont A16 63/63 T SAMETO | E60: MAP | F60: 1993 | H60: =IF(F60="","",YEAR(TODAY())-F60) -> 33 | I60: 120000 | J60: RGE 25 ans | K60: =IF(F60>2008,"Evaluation interne", " ") | L60: =IF(F60>2008, F60+20, " ") | M60: N | N60: =F60+39 -> 2032 | O60: 40000 | AA60: 170000 | BJ60: Pont A16 63/63 T SAMETO | BM60: 2028 | BQ60: Not Relevant
A61: 1-FRANCE | B61: UGB | C61: Pont A12 Caillard/SAMETO 63 T | D61: Elingue | E61: L21 | F61: 1974 | G61: RGE 1999 | H61: =IF(F61="","",YEAR(TODAY())-F61) -> 52 | I61: ='DEMARCHE EVS'!B9 -> 950000 | J61: RGE | K61: =IF(F61>2008,"Evaluation interne", " ") | L61: =IF(F61>2008, F61+20, " ") | M61: N | N61: 2027 | O61: 40000 | Q61: 60000 | T61: 160000 | W61: 40000 | AB61: 900000 | BD61: 2026 | BJ61: Pont A12 Caillard/SAMETO 63 T | BM61: 2028 | BN61: 2025 | BQ61: 2025
A62: 1-FRANCE | B62: UGB | C62: Semi-portique A16 10 T | F62: 1974 | H62: =IF(F62="","",YEAR(TODAY())-F62) -> 52 | J62: STOP-à remplacer par SP A15 | K62: =IF(F62>2008,"Evaluation interne", " ") | L62: =IF(F62>2008, F62+20, " ") | M62: O | N62: 2025 | O62: 25000 | Q62: =15000+25000 -> 40000 | BE62: 170000 | BJ62: Semi-portique A16 10 T | BK62: Manipulation | BM62: 2026 | BQ62: 2026
A63: 1-FRANCE | B63: UGB | C63: Pont A18 32/32T | E63: INJECTION | F63: 1974 | G63: RGE 2000 | H63: =IF(F63="","",YEAR(TODAY())-F63) -> 52 | I63: ='DEMARCHE EVS'!B6 -> 675000 | J63: Installation nouveaux ponts ou RGE | K63: =IF(F63>2008,"Evaluation interne", " ") | L63: =IF(F63>2008, F63+20, " ") | M63: N | N63: 2025 | O63: 40000 | T63: 40000 | X63: 170000 | AB63: 800000 | BJ63: Pont A18 32/32T | BM63: 2027 | BQ63: 2027
A64: 1-FRANCE | B64: UGB | C64: Pont A11 63/63 T CAILLARD/SAMETO ? | E64: HO | F64: 1974 | G64: RGE 2000 | H64: =IF(F64="","",YEAR(TODAY())-F64) -> 52 | I64: 1170000 | J64: RGE 25 ans | K64: =IF(F64>2008,"Evaluation interne", " ") | L64: =IF(F64>2008, F64+20, " ") | M64: N | N64: 2026 | O64: 40000 | T64: =40000 + 40000 -> 80000 | X64: 170000 | BD64: EGT | BJ64: Pont A11 63/63 T CAILLARD/SAMETO ? | BM64: 2027 | BQ64: >2027
A65: 1-FRANCE | B65: UPL | C65: Pont AA1 45 T SEVAL | D65: Elingue | F65: 2005 | H65: =IF(F65="","",YEAR(TODAY())-F65) -> 21 | J65: RGE | K65: =IF(F65>2008,"Evaluation interne", " ") | L65: =IF(F65>2008, F65+20, " ") | M65: N | N65: =F65+39 -> 2044 | O65: 40000 | AL65: 60000 | BD65: EGT | BJ65: Pont AA1 45 T SEVAL | BM65: 2032 | BQ65: COUT TOTAL : 40 K€
A66: 1-FRANCE | B66: UPL | C66: Pont AB3 50T SAMETO | D66: Elingue | F66: 2001 | H66: =IF(F66="","",YEAR(TODAY())-F66) -> 25 | I66: ='DEMARCHE EVS'!B8 -> 840000 | J66: RGE 25 ans | K66: =IF(F66>2008,"Evaluation interne", " ") | L66: =IF(F66>2008, F66+20, " ") | M66: N | N66: =F66+39 -> 2040 | O66: 40000 | AG66: 170000 | BD66: EGT | BJ66: Pont AB3 50T SAMETO | BM66: 2030 | BQ66: Briques Solution initiale :
A67: 1-FRANCE | B67: UPL | C67: Pont AA3 28T SEVAL | D67: Elingue | F67: 2001 | H67: =IF(F67="","",YEAR(TODAY())-F67) -> 25 | I67: ='DEMARCHE EVS'!B6 -> 675000 | J67: RGE 25 ans | K67: =IF(F67>2008,"Evaluation interne", " ") | L67: =IF(F67>2008, F67+20, " ") | M67: N | N67: =F67+39 -> 2040 | O67: 40000 | AG67: 170000 | BD67: EGT | BJ67: Pont AA3 28T SEVAL | BM67: 2030 | BQ67: - Périmètres de sécurité
A68: 1-FRANCE | B68: UPL | C68: Pont AB1 43 T SEVAL | D68: Elingue | E68: L12 | F68: 1997 | H68: =IF(F68="","",YEAR(TODAY())-F68) -> 29 | J68: RGE | K68: =IF(F68>2008,"Evaluation interne", " ") | L68: =IF(F68>2008, F68+20, " ") | M68: N | N68: =F68+39 -> 2036 | O68: 40000 | AA68: 170000 | BD68: EGT | BJ68: Pont AB1 43 T SEVAL | BM68: 2027 | BN68: 2025 | BO68: Confirmé Yannick | BQ68: Priorité 2 : ponts avec pinces (outils, bobines)
A69: 1-FRANCE | B69: UPL | C69: Pont AB2 40T SEVAL | D69: Pince | E69: L21/24 | F69: 1993 | H69: =IF(F69="","",YEAR(TODAY())-F69) -> 33 | J69: RGE | K69: =IF(F69>2008,"Evaluation interne", " ") | L69: =IF(F69>2008, F69+20, " ") | M69: N | N69: =F69+39 -> 2032 | O69: 40000 | X69: 25000 | BJ69: Pont AB2 40T SEVAL | BM69: 2026 | BQ69: Priorité 1 : Pont Transfert Outil avec élingues
A70: 1-FRANCE | B70: UPL | C70: Pont AA5 28 T SEVAL | D70: Elingue | E70: STOCKAGE | F70: 1993 | H70: =IF(F70="","",YEAR(TODAY())-F70) -> 33 | J70: RGE | K70: =IF(F70>2008,"Evaluation interne", " ") | L70: =IF(F70>2008, F70+20, " ") | M70: N | N70: =F70+39 -> 2032 | O70: 40000 | X70: 25000 | BD70: 2026B | BJ70: Pont AA5 28 T SEVAL | BM70: 2026 | BQ70: Priorité 1bis : Pont Obso (RGE prévue ou changement de pont)
A71: 1-FRANCE | B71: UPL | C71: Pont AB5 40 T SEVAL | D71: Elingue | E71: MAP | F71: 1993 | H71: =IF(F71="","",YEAR(TODAY())-F71) -> 33 | J71: RGE | K71: =IF(F71>2008,"Evaluation interne", " ") | L71: =IF(F71>2008, F71+20, " ") | M71: N | N71: =F71+39 -> 2032 | O71: 40000 | X71: 25000 | BJ71: Pont AB5 40 T SEVAL | BM71: asap | BQ71: 2024
A72: 1-FRANCE | B72: UPL | C72: Pont RAsud 32T CHSL | D72: Elingue | E72: STOCKAGE | F72: 1971 | G72: Projet pince 2026 | H72: =IF(F72="","",YEAR(TODAY())-F72) -> 55 | I72: 850000 | J72: Installation nouveaux ponts | K72: =IF(F72>2008,"Evaluation interne", " ") | L72: =IF(F72>2008, F72+20, " ") | M72: O | N72: =F72+39 -> 2010 | O72: 40000 | AF72: 40000 | AK72: 850000 | BJ72: Pont RAsud 32T CHSL | BM72: 2026
A73: 1-FRANCE | B73: UPL | C73: Pont RAcentre 32T CHSL | D73: Elingue | E73: STOCKAGE | F73: 1971 | H73: =IF(F73="","",YEAR(TODAY())-F73) -> 55 | I73: 860000 | J73: Installation nouveaux ponts | K73: =IF(F73>2008,"Evaluation interne", " ") | L73: =IF(F73>2008, F73+20, " ") | M73: N | N73: 2026 | O73: 40000 | T73: =40000 + 25000 -> 65000 | Y73: 860000 | BD73: EGT | BJ73: Pont RAcentre 32T CHSL | BM73: 2027 | BQ73: Eventgate : 15 K€ (facturé 18/20K€ par l'intégrateur)
A74: 1-FRANCE | B74: UPL | C74: Pont RA Nord 32T CHSL | D74: Elingue | E74: STOCKAGE | F74: 1971 | H74: =IF(F74="","",YEAR(TODAY())-F74) -> 55 | I74: ='DEMARCHE EVS'!B6 -> 675000 | J74: Installation nouveaux ponts | K74: =IF(F74>2008,"Evaluation interne", " ") | L74: =IF(F74>2008, F74+20, " ") | M74: N | N74: 2027 | O74: 40000 | W74: =40000 + 25000 -> 65000 | AB74: 860000 | BD74: EGT | BJ74: Pont RA Nord 32T CHSL | BM74: 2028 | BQ74: Intégrateur : 20 K€
A75: 1-FRANCE | B75: UPL | C75: Pont AB6. FLC/SAMETO. 50T | D75: Pince | E75: L62 | F75: 1969 | G75: rénovation en 2000 | H75: =IF(F75="","",YEAR(TODAY())-F75) -> 57 | I75: ='DEMARCHE EVS'!B8 -> 840000 | J75: RGE | K75: =IF(F75>2008,"Evaluation interne", " ") | L75: =IF(F75>2008, F75+20, " ") | M75: O | N75: =F75+39 -> 2008 | O75: 40000 | Q75: 50000 | W75: 40000 | BJ75: Pont AB6. FLC/SAMETO. 50T | BK75: Manutention | BM75: 2025
A76: 1-FRANCE | B76: UPL | C76: Pont AB4 Nord 15T APLEVAGE | D76: Elingue | E76: X | F76: 1958 | H76: =IF(F76="","",YEAR(TODAY())-F76) -> 68 | I76: 150000 | K76: =IF(F76>2008,"Evaluation interne", " ") | L76: =IF(F76>2008, F76+20, " ") | M76: O | N76: 2026 | T76: 4300 | BD76: EGT | BJ76: Pont AB4 Nord 15T APLEVAGE | BM76: asap
A77: 1-FRANCE | B77: UPL | C77: Pont AA4 6T APLEVAGE | D77: Elingue | E77: MAINTENANCE | F77: 1958 | H77: =IF(F77="","",YEAR(TODAY())-F77) -> 68 | I77: ='DEMARCHE EVS'!B4 -> 70000 | K77: =IF(F77>2008,"Evaluation interne", " ") | L77: =IF(F77>2008, F77+20, " ") | M77: O | N77: 2025 | O77: 8000 | Q77: 8000 | AF77: 8000 | BJ77: Pont AA4 6T APLEVAGE | BM77: asap | BQ77: Done
A78: 1-FRANCE | B78: UPL | C78: Pont AB4 sud 15T APLEVAGE | D78: Elingue | E78: L43 MP | F78: 1957 | H78: =IF(F78="","",YEAR(TODAY())-F78) -> 69 | I78: 150000 | K78: =IF(F78>2008,"Evaluation interne", " ") | L78: =IF(F78>2008, F78+20, " ") | M78: O | N78: 2026 | T78: 4300 | BJ78: Pont AB4 sud 15T APLEVAGE | BM78: asap | BQ78: - Bouées de détection assymétrique
A79: 1-FRANCE | B79: UPL | C79: Pince outils AB2 | D79: Pince | E79: L21/24 | F79: 2005 | H79: =IF(F79="","",YEAR(TODAY())-F79) -> 21 | J79: RG | K79: =IF(F79>2008,"Evaluation interne", " ") | L79: =IF(F79>2008, F79+20, " ") | M79: NC | N79: =F79+39 -> 2044 | X79: 90000
A80: 1-FRANCE | B80: UPL | C80: Pont AA2 6T LEVMAN | D80: Elingue | E80: RABOUTEUSES | F80: 1953 | H80: =IF(F80="","",YEAR(TODAY())-F80) -> 73 | K80: =IF(F80>2008,"Evaluation interne", " ") | L80: =IF(F80>2008, F80+20, " ") | M80: à désinvestir > sept 25 | BJ80: Pont AA2 6T LEVMAN | BM80: asap
A81: 1-FRANCE | B81: UPL | C81: Pince outils AB6 | D81: Pince | F81: 2005 | H81: =IF(F81="","",YEAR(TODAY())-F81) -> 21 | J81: RG | K81: =IF(F81>2008,"Evaluation interne", " ") | L81: =IF(F81>2008, F81+20, " ") | M81: NC | N81: =F81+39 -> 2044
A82: 1-FRANCE | B82: UPL | C82: Pont AF3 32T SAMETO | E82: Stockage outils | F82: 1971 | H82: =IF(F82="","",YEAR(TODAY())-F82) -> 55 | I82: ='DEMARCHE EVS'!B6 -> 675000 | M82: N | N82: 2026 | O82: 40,00 | T82: 40000 | X82: 170000
A83: 2-ESPAGNE | B83: PAL | C83: Pont 45/45T PG7 GH | D83: Elingue | F83: 2021 | H83: =IF(F83="","",YEAR(TODAY())-F83) -> 5 | K83: =IF(F83>2008,"Evaluation interne", " ") -> Evaluation interne | L83: =IF(F83>2008, F83+20, " ") -> 2041 | M83: N | N83: =F83+39 -> 2060 | O83: 40000 | BD83: 2026B | BJ83: Pont 45/45T PG7 GH
A84: 2-ESPAGNE | B84: PAL | C84: Pont 45/45T PG5 DEMAG High Speed | D84: Elingue | E84: XL HS | F84: 2017 | H84: =IF(F84="","",YEAR(TODAY())-F84) -> 9 | K84: =IF(F84>2008,"Evaluation interne", " ") -> Evaluation interne | L84: =IF(F84>2008, F84+20, " ") -> 2037 | M84: N | N84: =F84+20 -> 2037 | O84: 40000 | AS84: 170000 | BD84: EGT | BJ84: Pont 45/45T PG5 DEMAG High Speed | BN84: 2025
A85: 2-ESPAGNE | B85: PAL | C85: SP 25/25T SEVAL | D85: Elingue | F85: 2006 | H85: =IF(F85="","",YEAR(TODAY())-F85) -> 20 | J85: RGE 25 ans | K85: =IF(F85>2008,"Evaluation interne", " ") | L85: =IF(F85>2008, F85+20, " ") | M85: N | N85: =F85+39 -> 2045 | O85: 25000 | BJ85: SP 25/25T SEVAL | BK85: Manipulation | BM85: 2029
A86: 2-ESPAGNE | B86: PAL | C86: Pont 32/32T PG4 SEVAL | D86: Elingue | F86: 2005 | H86: =IF(F86="","",YEAR(TODAY())-F86) -> 21 | J86: RGE 25 ans | K86: =IF(F86>2008,"Evaluation interne", " ") | L86: =IF(F86>2008, F86+20, " ") | M86: N | N86: =F86+39 -> 2044 | O86: 40000 | AP86: 170000 | BD86: EGT | BJ86: Pont 32/32T PG4 SEVAL | BM86: 2028
A87: 2-ESPAGNE | B87: PAL | C87: Pont 63/63T PG1 SEVAL Matriceria | D87: Elingue | E87: MAINTENANCE | F87: 2004 | H87: =IF(F87="","",YEAR(TODAY())-F87) -> 22 | J87: RGE 25 ans | K87: =IF(F87>2008,"Evaluation interne", " ") | L87: =IF(F87>2008, F87+20, " ") | M87: N | N87: =F87+39 -> 2043 | O87: 40000 | AM87: 170000 | BJ87: Pont 63/63T PG1 SEVAL Matriceria | BM87: 2027
A88: 2-ESPAGNE | B88: PAL | C88: Pont 63T PG2 SEVAL L2 | D88: Elingue | E88: L02 | F88: 2002 | H88: =IF(F88="","",YEAR(TODAY())-F88) -> 24 | J88: RGE 25 ans | K88: =IF(F88>2008,"Evaluation interne", " ") | L88: =IF(F88>2008, F88+20, " ") | M88: N | N88: =F88+39 -> 2041 | O88: 40000 | AG88: 170000 | BD88: EGT | BJ88: Pont 63T PG2 SEVAL L2 | BM88: 2026
A89: 2-ESPAGNE | B89: PAL | C89: Pont 63T PG3 SEVAL L3 et 4 | D89: Elingue | E89: L03/L04 | F89: 2002 | H89: =IF(F89="","",YEAR(TODAY())-F89) -> 24 | I89: 1100000 | J89: RGE 25 ans | K89: =IF(F89>2008,"Evaluation interne", " ") | L89: =IF(F89>2008, F89+20, " ") | M89: N | N89: =F89+39 -> 2041 | O89: 40000 | U89: 329000 | AG89: 170000 | BD89: EGT | BE89: RPM S23 - att expertise | BJ89: Pont 63T PG3 SEVAL L3 et 4 | BM89: 2026
A90: 2-ESPAGNE | B90: PAL | C90: Pont 63/63T PG6 DEMAG | D90: Elingue | F90: 2001 | H90: =IF(F90="","",YEAR(TODAY())-F90) -> 25 | J90: RGE 25 ans | K90: =IF(F90>2008,"Evaluation interne", " ") | L90: =IF(F90>2008, F90+20, " ") | M90: N | N90: =F90+39 -> 2040 | O90: 40000 | AD90: 170000 | BD90: EGT | BJ90: Pont 63/63T PG6 DEMAG | BM90: 2026
A91: 2-ESPAGNE | B91: VLL | C91: Pont 40 T HOMANSER | F91: 2021 | H91: =IF(F91="","",YEAR(TODAY())-F91) -> 5 | K91: =IF(F91>2008,"Evaluation interne", " ") -> Evaluation interne | L91: =IF(F91>2008, F91+20, " ") -> 2041 | M91: N | N91: =F91+39 -> 2060 | O91: 40000 | BD91: EGT | BJ91: Pont 40 T HOMANSER
A92: 2-ESPAGNE | B92: VLL | C92: Pont 10 T HOMANSER | E92: X | F92: 2021 | H92: =IF(F92="","",YEAR(TODAY())-F92) -> 5 | K92: =IF(F92>2008,"Evaluation interne", " ") -> Evaluation interne | L92: =IF(F92>2008, F92+20, " ") -> 2041 | M92: N | N92: =F92+39 -> 2060 | O92: 40000 | BD92: EGT | BJ92: Pont 10 T HOMANSER
A93: 2-ESPAGNE | B93: VLL | C93: Pont 32 Tnord SEVAL bobines + retrofit DEMAG (2016) | D93: Pince | E93: BOBINES | F93: 2004 | H93: =IF(F93="","",YEAR(TODAY())-F93) -> 22 | J93: RG | K93: =IF(F93>2008,"Evaluation interne", " ") | L93: =IF(F93>2008, F93+20, " ") | M93: N | N93: =F93+39 -> 2043 | O93: 40000 | R93: 110000 | AM93: 170000 | BJ93: Pont 32 Tnord SEVAL bobines + retrofit DEMAG (2016) | BM93: 2025
A94: 2-ESPAGNE | B94: VLL | C94: Pont 32Tsud SEVAL bobines + retrofit DEMAG (2011) | D94: Pince | E94: BOBINES | F94: 2004 | H94: =IF(F94="","",YEAR(TODAY())-F94) -> 22 | J94: RGE | K94: =IF(F94>2008,"Evaluation interne", " ") | L94: =IF(F94>2008, F94+20, " ") | M94: N | N94: =F94+39 -> 2043 | O94: 40000 | R94: 110000 | AM94: 170000 | BJ94: Pont 32Tsud SEVAL bobines + retrofit DEMAG (2011) | BM94: 2025
A95: 2-ESPAGNE | B95: VLL | C95: Pont 32/32 T SEVAL Matricea 13a | D95: Elingue | E95: MAINTENANCE | F95: 2003 | H95: =IF(F95="","",YEAR(TODAY())-F95) -> 23 | J95: RGE | K95: =IF(F95>2008,"Evaluation interne", " ") | L95: =IF(F95>2008, F95+20, " ") | M95: N | N95: =F95+39 -> 2042 | O95: 40000 | AJ95: 170000 | BJ95: Pont 32/32 T SEVAL Matricea 13a | BM95: 2030
A96: 2-ESPAGNE | B96: VLL | C96: Pont 63/63 T SEVAL L13b | D96: Elingue | E96: L13B | F96: 2003 | H96: =IF(F96="","",YEAR(TODAY())-F96) -> 23 | J96: RGE | K96: =IF(F96>2008,"Evaluation interne", " ") | L96: =IF(F96>2008, F96+20, " ") | M96: N | N96: =F96+39 -> 2042 | O96: 40000 | AJ96: 170000 | BD96: EGT | BJ96: Pont 63/63 T SEVAL L13b | BM96: 2030
A97: 2-ESPAGNE | B97: VLL | C97: Pont 32/32 T SEVAL L11 | D97: Elingue | E97: L11 | F97: 2002 | H97: =IF(F97="","",YEAR(TODAY())-F97) -> 24 | J97: RGE | K97: =IF(F97>2008,"Evaluation interne", " ") | L97: =IF(F97>2008, F97+20, " ") | M97: N | N97: =F97+39 -> 2041 | O97: 40000 | AG97: 170000 | BD97: EGT | BJ97: Pont 32/32 T SEVAL L11 | BM97: 2029
A98: 2-ESPAGNE | B98: VLL | C98: Pont 63/63 T SEVAL L15 | D98: Elingue | E98: L15 | F98: 2002 | H98: =IF(F98="","",YEAR(TODAY())-F98) -> 24 | J98: RGE | K98: =IF(F98>2008,"Evaluation interne", " ") | L98: =IF(F98>2008, F98+20, " ") | M98: N | N98: =F98+39 -> 2041 | O98: 40000 | AG98: 170000 | BD98: EGT | BJ98: Pont 63/63 T SEVAL L15 | BM98: 2029
A99: 2-ESPAGNE | B99: VLL | C99: Pont 32/32 T SEVAL L5 | D99: Elingue | E99: L5/L6 | F99: 2001 | H99: =IF(F99="","",YEAR(TODAY())-F99) -> 25 | J99: RGE 25 ans | K99: =IF(F99>2008,"Evaluation interne", " ") | L99: =IF(F99>2008, F99+20, " ") | M99: N | N99: =F99+39 -> 2040 | O99: 40000 | AD99: 170000 | BD99: 2026 | BJ99: Pont 32/32 T SEVAL L5 | BM99: 2028 | BN99: 2025 | BO99: changement chef de dpt 16/04/25
A100: 2-ESPAGNE | B100: VLL | C100: Pont 32/32 T SEVAL L17 | D100: Elingue | E100: PPT L17 | F100: 2001 | H100: =IF(F100="","",YEAR(TODAY())-F100) -> 25 | J100: RGE 25 ans | K100: =IF(F100>2008,"Evaluation interne", " ") | L100: =IF(F100>2008, F100+20, " ") | M100: N | N100: =F100+39 -> 2040 | O100: 40000 | AD100: 170000 | BD100: EGT | BJ100: Pont 32/32 T SEVAL L17 | BM100: 2028
A101: 2-ESPAGNE | B101: VLL | C101: Pont 63/63 T ARAEL L1 | D101: Elingue | E101: L1 | F101: 2000 | H101: =IF(F101="","",YEAR(TODAY())-F101) -> 26 | J101: RGE | K101: =IF(F101>2008,"Evaluation interne", " ") | L101: =IF(F101>2008, F101+20, " ") | M101: N | N101: =F101+39 -> 2039 | O101: 40000 | AA101: 170000 | BD101: EGT | BJ101: Pont 63/63 T ARAEL L1 | BM101: 2027
...

Sheet SAUVPonts 160326 - maj
C2: A consolider | V2: A consolider
C3: EVS passée | V3: EVS passée
C4: En cas D'EVS négatif (changement pont) | V4: En cas D'EVS négatif (changement pont)
C5: Travaux spécifiques | V5: Travaux spécifiques
C6: RGE 25 ans | V6: RGE 25 ans
C7: RGE 50 ans | V7: RGE 50 ans
C8: EVS + tx suite EVS (réparation type soudures) | V8: EVS + tx suite EVS (réparation type soudures) OU dépenses obso (ex télécommandes)
B9: En Euros | K9: NEW ! | L9: NEW ! | M9: Evaluation Speciale | P9: OPEX usine = EVS + RGM après EVS + RGE après EVS (RGE "50 ans") CAPEX = RGE 25 ans + Installation nouveaux ponts (si EVS négatif) | BJ9: =COUNTA(BJ11:BJ182) -> 146 | BK9: ROADMAP SECURISATION DES PONTS
A10: PAYS | B10: Site | C10: Pont | D10: ACCESSOIRES : Pince ou Elingue | E10: Ligne de Presse ou utilisation | F10: MES | G10: Observations | H10: Age | I10: PRIX NEUF | J10: Travaux RG ou Installation Nouveau Pont | K10: Pont à évaluer en interne par Référent Levage (MES>2008) | L10: Année Evaluation Interne | M10: Evaluation Spéciale O/N | N10: EVS Année | O10: E/S Montant | P10: 2024 | Q10: 2025 OPEX DF (EVS et travaux préconisés) (EVS et travaux préconisés) | R10: 2025 RGE/RGM CAPEX IV | S10: 2025 ACHAT NEUF CAPEX IV | T10: 2026 OPEX DF (EVS et travaux préconisés) | U10: 2026 RGE/RGM CAPEX IV | V10: 2026 ACHAT NEUF CAPEX IV | W10: 2027 OPEX DF (EVS et travaux préconisés) | X10: 2027 RGE/RGM CAPEX IV | Y10: 2027 ACHAT NEUF CAPEX IV | Z10: 2028 OPEX DF (EVS et travaux préconisés) | AA10: 2028 RGE/RGM CAPEX IV | AB10: 2028 ACHAT NEUF CAPEX IV | AC10: 2029 OPEX DF (EVS et travaux préconisés) | AD10: 2029 RGE/RGM CAPEX IV | AE10: 2029 ACHAT NEUF CAPEX IV | AF10: 2030 OPEX DF (EVS et travaux préconisés) | AG10: 2030 RGE/RGM CAPEX IV | AH10: 2030 ACHAT NEUF CAPEX IV | AI10: 2031 OPEX DF (EVS et travaux préconisés) | AJ10: 2031 RGE/RGM CAPEX IV | AK10: 2031 ACHAT NEUF CAPEX IV | AL10: 2032 OPEX DF (EVS et travaux préconisés) | AM10: 2032 RGE/RGM CAPEX IV | AN10: 2032 ACHAT NEUF CAPEX IV | AO10: 2033 OPEX DF (EVS et travaux préconisés) | AP10: 2033 RGE/RGM CAPEX IV | AQ10: 2033 ACHAT NEUF CAPEX IV | AR10: 2034 OPEX DF (EVS et travaux préconisés) | AS10: 2034 RGE/RGM CAPEX IV | AT10: 2034 ACHAT NEUF CAPEX IV | AU10: 2035 OPEX DF (EVS et travaux préconisés) | AV10: 2035 RGE/RGM CAPEX IV | AW10: 2035 ACHAT NEUF CAPEX IV | AX10: 2036 OPEX DF (EVS et travaux préconisés) | AY10: 2036 RGE/RGM CAPEX IV | AZ10: 2036 ACHAT NEUF CAPEX IV | BA10: 2037 OPEX DF (EVS et travaux préconisés) | BB10: 2037 RGE/RGM CAPEX IV | BC10: 2037 ACHAT NEUF CAPEX IV | BD10: EGT | BE10: COMMENTAIRES ER SUIVI BAI | BK10: USAGE : Manutention et/ou Manipulation | BL10: TYPE : Automate ou Electromécanique | BM10: ROADMAP Capex Obsolescence | BN10: ROADMAP SECURISATION
A11: 1-FRANCE | B11: Chassis | C11: Pont E4 20T 48444 SEVAL/OMIS | F11: 2012 | G11: HORS SCOPE DEPT EMB | H11: =IF(F11="","",YEAR(TODAY())-F11) -> 14 | K11: =IF(F11>2008,"Evaluation interne", " ") -> Evaluation interne | L11: =IF(F11>2008, F11+20, " ") -> 2032 | M11: N | N11: =F11+39 -> 2051 | O11: 40000 | BJ11: Pont E4 20T 48444 SEVAL/OMIS
A12: 1-FRANCE | B12: Chassis | C12: Pont E0 46833 25 T KONECRANES | F12: 2010 | G12: HORS SCOPE DEPT EMB | H12: =IF(F12="","",YEAR(TODAY())-F12) -> 16 | J12: RGE | K12: =IF(F12>2008,"Evaluation interne", " ") -> Evaluation interne | L12: =IF(F12>2008, F12+20, " ") -> 2030 | M12: N | N12: =F12+39 -> 2049 | O12: 40000 | AU12: 40000 | BJ12: Pont E0 46833 25 T KONECRANES | BM12: 2035
A13: 1-FRANCE | B13: Chassis | C13: SP HH3 44839 25T ADC | F13: 2008 | G13: HORS SCOPE DEPT EMB | H13: =IF(F13="","",YEAR(TODAY())-F13) -> 18 | J13: RGE | K13: =IF(F13>2008,"Evaluation interne", " ") | L13: =IF(F13>2008, F13+20, " ") | M13: N | N13: =F13+39 -> 2047 | O13: 25000 | AO13: 50000 | BJ13: SP HH3 44839 25T ADC | BK13: Manipulation | BM13: 2033
A14: 1-FRANCE | B14: Chassis | C14: Pont E2 1470200822 4T SEVAL | F14: 2003 | G14: HORS SCOPE DEPT EMB | H14: =IF(F14="","",YEAR(TODAY())-F14) -> 23 | K14: =IF(F14>2008,"Evaluation interne", " ") | L14: =IF(F14>2008, F14+20, " ") | M14: N | N14: =F14+39 -> 2042 | O14: 40000 | BJ14: Pont E2 1470200822 4T SEVAL
A15: 1-FRANCE | B15: Chassis | C15: Pont E2' 1470200821 8/8 T DEMAG | F15: 2003 | G15: HORS SCOPE DEPT EMB | H15: =IF(F15="","",YEAR(TODAY())-F15) -> 23 | K15: =IF(F15>2008,"Evaluation interne", " ") | L15: =IF(F15>2008, F15+20, " ") | M15: N | N15: =F15+39 -> 2042 | O15: 40000 | BJ15: Pont E2' 1470200821 8/8 T DEMAG
A16: 1-FRANCE | B16: Chassis | C16: Pont E2 1470200820 14/14 T SEVAL | F16: 2003 | G16: HORS SCOPE DEPT EMB | H16: =IF(F16="","",YEAR(TODAY())-F16) -> 23 | J16: RGE | K16: =IF(F16>2008,"Evaluation interne", " ") | L16: =IF(F16>2008, F16+20, " ") | M16: N | N16: =F16+39 -> 2042 | O16: 40000 | AC16: 40000 | BJ16: Pont E2 1470200820 14/14 T SEVAL | BM16: 2029
A17: 1-FRANCE | B17: Chassis | C17: Pont (SP ?) E4 1470200756 8T | F17: 2003 | G17: HORS SCOPE DEPT EMB | H17: =IF(F17="","",YEAR(TODAY())-F17) -> 23 | J17: RGE | K17: =IF(F17>2008,"Evaluation interne", " ") | L17: =IF(F17>2008, F17+20, " ") | M17: N | N17: =F17+39 -> 2042 | O17: 40000 | Z17: 20000 | BJ17: Pont (SP ?) E4 1470200756 8T | BM17: 2028
A18: 1-FRANCE | B18: Chassis | C18: Pont E5 25 T 1470200554 SEVAL | F18: 2003 | G18: HORS SCOPE DEPT EMB | H18: =IF(F18="","",YEAR(TODAY())-F18) -> 23 | J18: RGE | K18: =IF(F18>2008,"Evaluation interne", " ") | L18: =IF(F18>2008, F18+20, " ") | M18: N | N18: =F18+39 -> 2042 | O18: 40000 | Z18: 50000 | BJ18: Pont E5 25 T 1470200554 SEVAL | BM18: 2028
A19: 1-FRANCE | B19: Chassis | C19: Pont E6 1470000240 50T SAMETO | F19: 2001 | G19: HORS SCOPE DEPT EMB | H19: =IF(F19="","",YEAR(TODAY())-F19) -> 25 | J19: RGE 25 ans | K19: =IF(F19>2008,"Evaluation interne", " ") | L19: =IF(F19>2008, F19+20, " ") | M19: N | N19: =F19+39 -> 2040 | O19: 40000 | X19: 170000 | BJ19: Pont E6 1470000240 50T SAMETO | BM19: 2027 | BN19: 2025
A20: 1-FRANCE | B20: Chassis | C20: Pont E6 1470001297 50/50T SAMETO | F20: 2001 | G20: HORS SCOPE DEPT EMB | H20: =IF(F20="","",YEAR(TODAY())-F20) -> 25 | J20: RGE 25 ans | K20: =IF(F20>2008,"Evaluation interne", " ") | L20: =IF(F20>2008, F20+20, " ") | M20: N | N20: =F20+39 -> 2040 | O20: 40000 | X20: 170000 | BJ20: Pont E6 1470001297 50/50T SAMETO | BM20: 2027
A21: 1-FRANCE | B21: Chassis | C21: Pont E0 1470000704 25 T SEVAL | F21: 2000 | G21: HORS SCOPE DEPT EMB | H21: =IF(F21="","",YEAR(TODAY())-F21) -> 26 | J21: RGE | K21: =IF(F21>2008,"Evaluation interne", " ") | L21: =IF(F21>2008, F21+20, " ") | M21: N | N21: =F21+39 -> 2039 | O21: 40000 | U21: 150000 | BJ21: Pont E0 1470000704 25 T SEVAL | BM21: 2026
A22: 1-FRANCE | B22: Chassis | C22: Pont E2 1479900509 16T SAMETO | F22: 1999 | G22: HORS SCOPE DEPT EMB | H22: =IF(F22="","",YEAR(TODAY())-F22) -> 27 | J22: RGE | K22: =IF(F22>2008,"Evaluation interne", " ") | L22: =IF(F22>2008, F22+20, " ") | M22: N | N22: =F22+39 -> 2038 | O22: 40000 | U22: 120000 | BJ22: Pont E2 1479900509 16T SAMETO | BM22: 2026
A23: 1-FRANCE | B23: Chassis | C23: Pont E1 759847 20T SAMETO | F23: 1994 | G23: HORS SCOPE DEPT EMB | H23: =IF(F23="","",YEAR(TODAY())-F23) -> 32 | J23: RGE | K23: =IF(F23>2008,"Evaluation interne", " ") | L23: =IF(F23>2008, F23+20, " ") | M23: N | N23: =F23+39 -> 2033 | O23: 40000 | U23: 150000 | BJ23: Pont E1 759847 20T SAMETO | BM23: 2026
A24: 1-FRANCE | B24: Chassis | C24: Pont E1 759848 20/20 T SAMETO (RGE 2019) | F24: 1994 | G24: HORS SCOPE DEPT EMB | H24: =IF(F24="","",YEAR(TODAY())-F24) -> 32 | K24: =IF(F24>2008,"Evaluation interne", " ") | L24: =IF(F24>2008, F24+20, " ") | M24: N | N24: =F24+39 -> 2033 | O24: 40000 | BJ24: Pont E1 759848 20/20 T SAMETO (RGE 2019)
A25: 1-FRANCE | B25: LHA | C25: Pont J12 63T | D25: Pince | E25: L08 | F25: 2006 | H25: =IF(F25="","",YEAR(TODAY())-F25) -> 20 | I25: ='DEMARCHE EVS'!B9 -> 950000 | J25: RGE | K25: =IF(F25>2008,"Evaluation interne", " ") | L25: =IF(F25>2008, F25+20, " ") | M25: NC | N25: =F25+39 -> 2045 | O25: 40000 | Z25: 60000 | BJ25: Pont J12 | BM25: 2028
A26: 1-FRANCE | B26: LHA | C26: Pont J11 63T | D26: Pince | E26: L11 | F26: 2006 | H26: =IF(F26="","",YEAR(TODAY())-F26) -> 20 | J26: RGE | K26: =IF(F26>2008,"Evaluation interne", " ") | L26: =IF(F26>2008, F26+20, " ") | N26: =F26+39 -> 2045 | O26: 40000 | AJ26: 170000 | BJ26: Pont J11 | BM26: 2029
A27: 1-FRANCE | B27: LHA | C27: Pince outils J11 | D27: PINCE | E27: L11 | F27: 1999 | H27: =IF(F27="","",YEAR(TODAY())-F27) -> 27 | J27: RG | K27: =IF(F27>2008,"Evaluation interne", " ") | L27: =IF(F27>2008, F27+20, " ") | M27: NC | R27: 100000
A28: 1-FRANCE | B28: LHA | C28: Pince à outil J12 | D28: PINCE | E28: STOCKAGE | F28: 1999 | H28: =IF(F28="","",YEAR(TODAY())-F28) -> 27 | I28: 220000 | J28: RGM | K28: =IF(F28>2008,"Evaluation interne", " ") | L28: =IF(F28>2008, F28+20, " ") | M28: NC | U28: 85000
A29: 1-FRANCE | B29: LHA | C29: Semi-portique N°1 J3 CHSL | E29: n fc | F29: 1979 | H29: =IF(F29="","",YEAR(TODAY())-F29) -> 47 | I29: 120000 | J29: RG | K29: =IF(F29>2008,"Evaluation interne", " ") | L29: =IF(F29>2008, F29+20, " ") | M29: N | N29: 2026 | O29: 20000 | T29: 20000 | BJ29: Semi-portique N°1 J3 CHSL | BK29: Manipulation
A30: 1-FRANCE | B30: LHA | C30: Semi-portique N°2 J3 CHSL (10T SAMETO?)-STOP 06/02 | E30: MAP/MAINTENANCE | F30: 1979 | H30: =IF(F30="","",YEAR(TODAY())-F30) -> 47 | I30: 120000 | J30: RG | K30: =IF(F30>2008,"Evaluation interne", " ") | L30: =IF(F30>2008, F30+20, " ") | M30: N | N30: 2026 | O30: 20000 | T30: =20000 -> 20000 | BJ30: Semi-portqiue N°2 J3 CHSL | BK30: Manipulation
A31: 1-FRANCE | B31: LHA | C31: Pont J1sud 63T | E31: 80%OUTILS / 20%BOBINES | F31: 1970 | H31: =IF(F31="","",YEAR(TODAY())-F31) -> 56 | J31: RGE 50 ans | K31: =IF(F31>2008,"Evaluation interne", " ") | L31: =IF(F31>2008, F31+20, " ") | M31: O | N31: 2035 | O31: 40000 | Q31: =40000 + 25000 -> 65000 | X31: 170000 | AU31: 40000 | AZ31: 1120000 | BJ31: Pont J1sud 63T | BM31: 2026
A32: 1-FRANCE | B32: LHA | C32: Pont J3 63/63T CAILLARD | E32: MAP/MAINTENANCE | F32: 1970 | H32: =IF(F32="","",YEAR(TODAY())-F32) -> 56 | I32: 1170000 | J32: 2026 prov pour travaux / Installation nouveaux ponts 2027 | K32: =IF(F32>2008,"Evaluation interne", " ") | L32: =IF(F32>2008, F32+20, " ") | M32: N | N32: 2026 | O32: 40000 | T32: 69000 | X32: 170000 | AB32: 1170000 | BJ32: Pont J3 63/63T CAILLARD | BM32: 2026
A33: 1-FRANCE | B33: LHA | C33: Chemins de roulement J3 | E33: MAP/MAINTENANCE | F33: 1970 | H33: =IF(F33="","",YEAR(TODAY())-F33) -> 56 | I33: nc | J33: RG | K33: =IF(F33>2008,"Evaluation interne", " ") | L33: =IF(F33>2008, F33+20, " ") | M33: NC | BJ33: Chemins de roulement J3
A34: 1-FRANCE | B34: LHA | C34: Chemins de roulement J1 SUD 63T, soudures | E34: BOBINES | F34: 1970 | H34: =IF(F34="","",YEAR(TODAY())-F34) -> 56 | I34: nc | J34: RG | K34: =IF(F34>2008,"Evaluation interne", " ") | L34: =IF(F34>2008, F34+20, " ") | M34: NC | BJ34: Chemins de roulement J1, soudures
A35: 1-FRANCE | B35: LHA | C35: J1 Nord | D35: Pince | E35: STOCKAGE | H35: =IF(F35="","",YEAR(TODAY())-F35) | K35: =IF(F35>2008,"Evaluation interne", " ") | L35: =IF(F35>2008, F35+20, " ") | BJ35: J1 Nord
A36: 1-FRANCE | B36: LHA | C36: J2 Nord | D36: Elingue | E36: STOCKAGE | H36: =IF(F36="","",YEAR(TODAY())-F36) | K36: =IF(F36>2008,"Evaluation interne", " ") | L36: =IF(F36>2008, F36+20, " ") | BD36: EGT | BJ36: J2 Nord | BN36: 2025
A37: 1-FRANCE | B37: LHA | C37: J2 Sud | D37: Elingue | E37: PAL/PAVAR | H37: =IF(F37="","",YEAR(TODAY())-F37) | K37: =IF(F37>2008,"Evaluation interne", " ") | L37: =IF(F37>2008, F37+20, " ") | BD37: 2026 | BJ37: J2 Sud
A38: 1-FRANCE | B38: MCA | C38: Pont 63T XLHS SECAL | D38: Pince | E38: XL HS | F38: 2019 | H38: =IF(F38="","",YEAR(TODAY())-F38) -> 7 | K38: =IF(F38>2008,"Evaluation interne", " ") -> Evaluation interne | L38: =IF(F38>2008, F38+20, " ") -> 2039 | M38: N | N38: =F38+20 -> 2039 | O38: 40000 | AA38: 140000 | BJ38: Pont 63T XLHS SECAL | BM38: 2028
A39: 1-FRANCE | B39: MCA | C39: PINCE 50T XXL HS | E39: XXL HS | F39: 2019 | H39: =IF(F39="","",YEAR(TODAY())-F39) -> 7 | K39: =IF(F39>2008,"Evaluation interne", " ") -> Evaluation interne | L39: =IF(F39>2008, F39+20, " ") -> 2039 | N39: 2039
A40: 1-FRANCE | B40: MCA | C40: Pont 50/50 T XLHS SECAL | D40: Pince | E40: MAP XL | F40: 2019 | H40: =IF(F40="","",YEAR(TODAY())-F40) -> 7 | K40: =IF(F40>2008,"Evaluation interne", " ") -> Evaluation interne | L40: =IF(F40>2008, F40+20, " ") -> 2039 | M40: N | N40: =F40+39 -> 2058 | O40: 40000 | AD40: 170000 | BJ40: Pont 50/50 T XLHS SECAL | BM40: 2029
A41: 1-FRANCE | B41: MCA | C41: Pont 25 T PAL SEVAL | D41: Elingue | E41: PAL | F41: 2001 | H41: =IF(F41="","",YEAR(TODAY())-F41) -> 25 | J41: RGE 25 ans | K41: =IF(F41>2008,"Evaluation interne", " ") | L41: =IF(F41>2008, F41+20, " ") | M41: N | N41: =F41+39 -> 2040 | O41: 40000 | R41: 135000 | V41: 290000 | BD41: EGT | BJ41: Pont 25 T PAL SEVAL | BM41: 2025
A42: 1-FRANCE | B42: MCA | C42: Pont 32 T Appro bobines SAMETO | D42: Pince | E42: BOBINES | F42: 2000 | H42: =IF(F42="","",YEAR(TODAY())-F42) -> 26 | J42: RGE 25 ans | K42: =IF(F42>2008,"Evaluation interne", " ") | L42: =IF(F42>2008, F42+20, " ") | M42: N | N42: =F42+39 -> 2039 | O42: 40000 | AA42: 170000 | BJ42: Pont 32 T Appro bobines SAMETO | BM42: 2027
A43: 1-FRANCE | B43: MCA | C43: Pont 25/25T Nord SAMETO | D43: Elingue | E43: MAP (et ex L3) | F43: 1998 | H43: =IF(F43="","",YEAR(TODAY())-F43) -> 28 | J43: RGE 25 ans | K43: =IF(F43>2008,"Evaluation interne", " ") | L43: =IF(F43>2008, F43+20, " ") | M43: N | N43: =F43+39 -> 2037 | O43: 40000 | X43: 0 | BJ43: Pont 25/25T Nord SAMETO | BM43: 2025 | BN43: 2025
A44: 1-FRANCE | B44: MCA | C44: Semi-portique 25/25 T surclassé 30T SEVAL | E44: MAP/travée 5400T | F44: 1996 | H44: =IF(F44="","",YEAR(TODAY())-F44) -> 30 | J44: RGE 25 ans | K44: =IF(F44>2008,"Evaluation interne", " ") | L44: =IF(F44>2008, F44+20, " ") | M44: N | N44: 2035 | O44: 25000 | X44: 170000 | BJ44: Semi-portique 25/25 T surclassé 30T SEVAL | BM44: 2026
A45: 1-FRANCE | B45: MCA | C45: Pont 80T SAMETO | D45: Pince | E45: PT5400 | F45: 1995 | H45: =IF(F45="","",YEAR(TODAY())-F45) -> 31 | J45: RGE 25 ans | K45: =IF(F45>2008,"Evaluation interne", " ") | L45: =IF(F45>2008, F45+20, " ") | M45: N | N45: 2034 | O45: 40000 | X45: 0 | BJ45: Pont 80T SAMETO | BM45: 2026
A46: 1-FRANCE | B46: MCA | C46: Pont 25/25 T Sud SEVAL L01 | D46: Elingue | E46: L01 | F46: 1994 | H46: =IF(F46="","",YEAR(TODAY())-F46) -> 32 | J46: RGE 25 ans | K46: =IF(F46>2008,"Evaluation interne", " ") | L46: =IF(F46>2008, F46+20, " ") | M46: N | N46: 2033 | O46: 40000 | X46: 170000 | BD46: 2026B | BE46: 170000 | BJ46: Pont 25/25 T Sud SEVAL | BM46: 2027
A47: 1-FRANCE | B47: UGB | C47: Pont A14 63/63 T ADC | E47: X MP | F47: 2019 | H47: =IF(F47="","",YEAR(TODAY())-F47) -> 7 | K47: =IF(F47>2008,"Evaluation interne", " ") -> Evaluation interne | L47: =IF(F47>2008, F47+20, " ") -> 2039 | M47: N | N47: =F47+39 -> 2058 | O47: 40000 | BD47: EGT | BJ47: Pont A14 63/63 T ADC
A48: 1-FRANCE | B48: UGB | C48: Pont A1 GE 35 T SECAL | D48: Pince | E48: BOBINES | F48: 2016 | H48: =IF(F48="","",YEAR(TODAY())-F48) -> 10 | K48: =IF(F48>2008,"Evaluation interne", " ") -> Evaluation interne | L48: =IF(F48>2008, F48+20, " ") -> 2036 | M48: N | N48: =F48+39 -> 2055 | O48: 40000 | BJ48: Pont A1 GE 35 T SECAL | BM48: Pince
A49: 1-FRANCE | B49: UGB | C49: Pont A13 80 T SECAL/OMIS | D49: Pince | E49: PT5400 | F49: 2015 | H49: =IF(F49="","",YEAR(TODAY())-F49) -> 11 | K49: =IF(F49>2008,"Evaluation interne", " ") -> Evaluation interne | L49: =IF(F49>2008, F49+20, " ") -> 2035 | M49: N | N49: =F49+39 -> 2054 | O49: 40000 | BJ49: Pont A13 80 T SECAL/OMIS
A50: 1-FRANCE | B50: UGB | C50: Pont A15 50/50 T SEVAL/OMIS | E50: X | F50: 2012 | H50: =IF(F50="","",YEAR(TODAY())-F50) -> 14 | K50: =IF(F50>2008,"Evaluation interne", " ") -> Evaluation interne | L50: =IF(F50>2008, F50+20, " ") -> 2032 | M50: N | N50: =F50+39 -> 2051 | O50: 40000 | BD50: EGT | BJ50: Pont A15 50/50 T SEVAL/OMIS
A51: 1-FRANCE | B51: UGB | C51: Pont A1 PE 35 T KONECRANES | D51: Pince | E51: BOBINES | F51: 2010 | H51: =IF(F51="","",YEAR(TODAY())-F51) -> 16 | J51: RGE 25 ans | K51: =IF(F51>2008,"Evaluation interne", " ") -> Evaluation interne | L51: =IF(F51>2008, F51+20, " ") -> 2030 | M51: N | N51: =F51+39 -> 2049 | O51: 40000 | AF51: 40000 | AV51: 170000 | BJ51: Pont A1 PE 35 T KONECRANES | BM51: 2035
A52: 1-FRANCE | B52: UGB | C52: Pont A17 35 T SEVAL/OMIS | E52: INJECTION | F52: 2009 | H52: =IF(F52="","",YEAR(TODAY())-F52) -> 17 | K52: =IF(F52>2008,"Evaluation interne", " ") -> Evaluation interne | L52: =IF(F52>2008, F52+20, " ") -> 2029 | M52: N | N52: =F52+39 -> 2048 | O52: 40000 | BJ52: Pont A17 35 T SEVAL/OMIS
A53: 1-FRANCE | B53: UGB | C53: Pont A2 GE 35 T KONECRANES | D53: Elingue | E53: DECOUPES | F53: 2008 | H53: =IF(F53="","",YEAR(TODAY())-F53) -> 18 | J53: RGE 25 ans | K53: =IF(F53>2008,"Evaluation interne", " ") | L53: =IF(F53>2008, F53+20, " ") | M53: N | N53: =F53+39 -> 2047 | O53: 40000 | AP53: 170000 | BD53: EGT | BJ53: Pont A2 GE 35 T KONECRANES | BM53: 2033
A54: 1-FRANCE | B54: UGB | C54: Pont A2 PE 35 T KONECRANES | D54: Elingue | E54: DECOUPES | F54: 2006 | H54: =IF(F54="","",YEAR(TODAY())-F54) -> 20 | J54: RGE 25 ans | K54: =IF(F54>2008,"Evaluation interne", " ") | L54: =IF(F54>2008, F54+20, " ") | M54: N | N54: =F54+39 -> 2045 | O54: 40000 | AJ54: 170000 | BD54: EGT | BJ54: Pont A2 PE 35 T KONECRANES | BM54: 2031
A55: 1-FRANCE | B55: UGB | C55: Pont A9 63/63 T KONECRANES | E55: MAINTENANCE/MAP | F55: 2005 | H55: =IF(F55="","",YEAR(TODAY())-F55) -> 21 | J55: RGE 25 ans | K55: =IF(F55>2008,"Evaluation interne", " ") | L55: =IF(F55>2008, F55+20, " ") | M55: N | N55: =F55+39 -> 2044 | O55: 40000 | AG55: 170000 | BJ55: Pont A9 63/63 T KONECRANES | BM55: 2030
A56: 1-FRANCE | B56: UGB | C56: Pont A7 63/63 T SEVAL | D56: Elingue | E56: STOCKAGE | F56: 2004 | H56: =IF(F56="","",YEAR(TODAY())-F56) -> 22 | J56: RGE 25 ans | K56: =IF(F56>2008,"Evaluation interne", " ") | L56: =IF(F56>2008, F56+20, " ") | M56: N | N56: =F56+39 -> 2043 | O56: 40000 | AD56: 170000 | BD56: EGT | BJ56: Pont A7 63/63 T SEVAL | BM56: 2029
A57: 1-FRANCE | B57: UGB | C57: Pont A8 63/63 T SAMETO | D57: Elingue | E57: L12 | F57: 2001 | H57: =IF(F57="","",YEAR(TODAY())-F57) -> 25 | I57: 1170000 | J57: RGE 25 ans | K57: =IF(F57>2008,"Evaluation interne", " ") | L57: =IF(F57>2008, F57+20, " ") | M57: N | N57: =F57+39 -> 2040 | O57: 40000 | X57: 170000 | AD57: 170000 | BD57: EGT | BJ57: Pont A8 63/63 T SAMETO | BM57: 2026 | BN57: 2026 | BO57: était prévu 2025, budget 25 transféré à CVP
A58: 1-FRANCE | B58: UGB | C58: Pont A2 50 T SAMETO | D58: Elingue | E58: DECOUPES | F58: 2001 | G58: AC installé en 2018 suite usure galets | H58: =IF(F58="","",YEAR(TODAY())-F58) -> 25 | J58: RGE 25 ans | K58: =IF(F58>2008,"Evaluation interne", " ") | L58: =IF(F58>2008, F58+20, " ") | M58: N | N58: =F58+39 -> 2040 | O58: 40000 | AA58: 170000 | BD58: EGT | BJ58: Pont A2 50 T SAMETO | BM58: 2027
A59: 1-FRANCE | B59: UGB | C59: Pont A10 63/63 T SAMETO | E59: X L17 | F59: 1996 | H59: =IF(F59="","",YEAR(TODAY())-F59) -> 30 | J59: RGE 25 ans | K59: =IF(F59>2008,"Evaluation interne", " ") | L59: =IF(F59>2008, F59+20, " ") | M59: N | N59: =F59+39 -> 2035 | O59: 40000 | X59: 170000 | BD59: EGT | BJ59: Pont A10 63/63 T SAMETO | BM59: 2027
A60: 1-FRANCE | B60: UGB | C60: Pont A16 63/63 T SAMETO | E60: MAP | F60: 1993 | H60: =IF(F60="","",YEAR(TODAY())-F60) -> 33 | I60: 120000 | J60: RGE 25 ans | K60: =IF(F60>2008,"Evaluation interne", " ") | L60: =IF(F60>2008, F60+20, " ") | M60: N | N60: =F60+39 -> 2032 | O60: 40000 | AA60: 170000 | BJ60: Pont A16 63/63 T SAMETO | BM60: 2028 | BQ60: Not Relevant
A61: 1-FRANCE | B61: UGB | C61: Pont A12 Caillard/SAMETO 63 T | D61: Elingue | E61: L21 | F61: 1974 | G61: RGE 1999 | H61: =IF(F61="","",YEAR(TODAY())-F61) -> 52 | I61: ='DEMARCHE EVS'!B9 -> 950000 | J61: RGE | K61: =IF(F61>2008,"Evaluation interne", " ") | L61: =IF(F61>2008, F61+20, " ") | M61: N | N61: 2027 | O61: 40000 | Q61: 60000 | T61: 160000 | W61: 40000 | AB61: 900000 | BD61: 2026 | BJ61: Pont A12 Caillard/SAMETO 63 T | BM61: 2028 | BN61: 2025 | BQ61: 2025
A62: 1-FRANCE | B62: UGB | C62: Semi-portique A16 10 T | F62: 1974 | H62: =IF(F62="","",YEAR(TODAY())-F62) -> 52 | J62: STOP-à remplacer par SP A15 | K62: =IF(F62>2008,"Evaluation interne", " ") | L62: =IF(F62>2008, F62+20, " ") | M62: O | N62: 2025 | O62: 25000 | Q62: =15000+25000 -> 40000 | BE62: 170000 | BJ62: Semi-portique A16 10 T | BK62: Manipulation | BM62: 2026 | BQ62: 2026
A63: 1-FRANCE | B63: UGB | C63: Pont A18 32/32T | E63: INJECTION | F63: 1974 | G63: RGE 2000 | H63: =IF(F63="","",YEAR(TODAY())-F63) -> 52 | I63: ='DEMARCHE EVS'!B6 -> 675000 | J63: Installation nouveaux ponts ou RGE | K63: =IF(F63>2008,"Evaluation interne", " ") | L63: =IF(F63>2008, F63+20, " ") | M63: N | N63: 2025 | O63: 40000 | T63: 40000 | X63: 170000 | AB63: 800000 | BJ63: Pont A18 32/32T | BM63: 2027 | BQ63: 2027
A64: 1-FRANCE | B64: UGB | C64: Pont A11 63/63 T CAILLARD/SAMETO ? | E64: HO | F64: 1974 | G64: RGE 2000 | H64: =IF(F64="","",YEAR(TODAY())-F64) -> 52 | I64: 1170000 | J64: RGE 25 ans | K64: =IF(F64>2008,"Evaluation interne", " ") | L64: =IF(F64>2008, F64+20, " ") | M64: N | N64: 2026 | O64: 40000 | T64: =40000 + 40000 -> 80000 | X64: 170000 | BD64: EGT | BJ64: Pont A11 63/63 T CAILLARD/SAMETO ? | BM64: 2027 | BQ64: >2027
A65: 1-FRANCE | B65: UPL | C65: Pont AA1 45 T SEVAL | D65: Elingue | F65: 2005 | H65: =IF(F65="","",YEAR(TODAY())-F65) -> 21 | J65: RGE | K65: =IF(F65>2008,"Evaluation interne", " ") | L65: =IF(F65>2008, F65+20, " ") | M65: N | N65: =F65+39 -> 2044 | O65: 40000 | AL65: 60000 | BD65: EGT | BJ65: Pont AA1 45 T SEVAL | BM65: 2032 | BQ65: COUT TOTAL : 40 K€
A66: 1-FRANCE | B66: UPL | C66: Pince outils AB2 | D66: Pince | E66: L21/24 | F66: 2005 | H66: =IF(F66="","",YEAR(TODAY())-F66) -> 21 | J66: RG | K66: =IF(F66>2008,"Evaluation interne", " ") | L66: =IF(F66>2008, F66+20, " ") | M66: NC | N66: =F66+39 -> 2044 | O66: 40000 | X66: 90000
A67: 1-FRANCE | B67: UPL | C67: Pince outils AB6 | D67: Pince | F67: 2005 | H67: =IF(F67="","",YEAR(TODAY())-F67) -> 21 | J67: RG | K67: =IF(F67>2008,"Evaluation interne", " ") | L67: =IF(F67>2008, F67+20, " ") | M67: NC | N67: =F67+39 -> 2044 | X67: 90000
A68: 1-FRANCE | B68: UPL | C68: Pont AB3 50T SAMETO | D68: Elingue | F68: 2001 | H68: =IF(F68="","",YEAR(TODAY())-F68) -> 25 | I68: ='DEMARCHE EVS'!B8 -> 840000 | J68: RGE 25 ans | K68: =IF(F68>2008,"Evaluation interne", " ") | L68: =IF(F68>2008, F68+20, " ") | M68: N | N68: =F68+39 -> 2040 | O68: 40000 | AG68: 170000 | BD68: EGT | BJ68: Pont AB3 50T SAMETO | BM68: 2030 | BQ68: Briques Solution initiale :
A69: 1-FRANCE | B69: UPL | C69: Pont AA3 28T SEVAL | D69: Elingue | F69: 2001 | H69: =IF(F69="","",YEAR(TODAY())-F69) -> 25 | I69: ='DEMARCHE EVS'!B6 -> 675000 | J69: RGE 25 ans | K69: =IF(F69>2008,"Evaluation interne", " ") | L69: =IF(F69>2008, F69+20, " ") | M69: N | N69: =F69+39 -> 2040 | O69: 40000 | AG69: 170000 | BD69: EGT | BJ69: Pont AA3 28T SEVAL | BM69: 2030 | BQ69: - Périmètres de sécurité
A70: 1-FRANCE | B70: UPL | C70: Pont AB1 43 T SEVAL | D70: Elingue | E70: L12 | F70: 1997 | H70: =IF(F70="","",YEAR(TODAY())-F70) -> 29 | J70: RGE | K70: =IF(F70>2008,"Evaluation interne", " ") | L70: =IF(F70>2008, F70+20, " ") | M70: N | N70: =F70+39 -> 2036 | O70: 40000 | BD70: EGT | BJ70: Pont AB1 43 T SEVAL | BM70: 2027 | BN70: 2025 | BO70: Confirmé Yannick | BQ70: Priorité 2 : ponts avec pinces (outils, bobines)
A71: 1-FRANCE | B71: UPL | C71: Pont AB2 40T SEVAL | D71: Pince | E71: L21/24 | F71: 1993 | H71: =IF(F71="","",YEAR(TODAY())-F71) -> 33 | J71: RGE 25 ans | K71: =IF(F71>2008,"Evaluation interne", " ") | L71: =IF(F71>2008, F71+20, " ") | M71: N | N71: =F71+39 -> 2032 | O71: 40000 | X71: 25000 | BJ71: Pont AB2 40T SEVAL | BM71: 2026 | BQ71: Priorité 1 : Pont Transfert Outil avec élingues
A72: 1-FRANCE | B72: UPL | C72: Pont AA5 28 T SEVAL | D72: Elingue | E72: STOCKAGE | F72: 1993 | H72: =IF(F72="","",YEAR(TODAY())-F72) -> 33 | J72: RGE 25 ans | K72: =IF(F72>2008,"Evaluation interne", " ") | L72: =IF(F72>2008, F72+20, " ") | M72: N | N72: =F72+39 -> 2032 | O72: 40000 | X72: 25000 | BD72: 2026B | BJ72: Pont AA5 28 T SEVAL | BM72: 2026 | BQ72: Priorité 1bis : Pont Obso (RGE prévue ou changement de pont)
A73: 1-FRANCE | B73: UPL | C73: Pont AB5 40 T SEVAL | D73: Elingue | E73: MAP | F73: 1993 | H73: =IF(F73="","",YEAR(TODAY())-F73) -> 33 | J73: RGE 25 ans | K73: =IF(F73>2008,"Evaluation interne", " ") | L73: =IF(F73>2008, F73+20, " ") | M73: N | N73: =F73+39 -> 2032 | O73: 40000 | X73: 25000 | BJ73: Pont AB5 40 T SEVAL | BM73: asap | BQ73: 2024
A74: 1-FRANCE | B74: UPL | C74: Pont RAsud 32T CHSL | D74: Elingue | E74: STOCKAGE | F74: 1971 | G74: Projet pince 2026 en cours | H74: =IF(F74="","",YEAR(TODAY())-F74) -> 55 | I74: 850000 | J74: Installation nouveaux ponts | K74: =IF(F74>2008,"Evaluation interne", " ") | L74: =IF(F74>2008, F74+20, " ") | M74: O | N74: =F74+39 -> 2010 | O74: 40000 | AF74: 40000 | AK74: 850000 | BJ74: Pont RAsud 32T CHSL | BM74: 2026
A75: 1-FRANCE | B75: UPL | C75: Pont RAcentre 32T CHSL | D75: Elingue | E75: STOCKAGE | F75: 1971 | H75: =IF(F75="","",YEAR(TODAY())-F75) -> 55 | I75: 860000 | J75: Installation nouveaux ponts | K75: =IF(F75>2008,"Evaluation interne", " ") | L75: =IF(F75>2008, F75+20, " ") | M75: N | N75: 2026 | O75: 40000 | T75: =40000 + 25000 -> 65000 | Y75: 860000 | BD75: EGT | BJ75: Pont RAcentre 32T CHSL | BM75: 2027 | BQ75: Eventgate : 15 K€ (facturé 18/20K€ par l'intégrateur)
A76: 1-FRANCE | B76: UPL | C76: Pont RA Nord 32T CHSL | D76: Elingue | E76: STOCKAGE | F76: 1971 | H76: =IF(F76="","",YEAR(TODAY())-F76) -> 55 | I76: ='DEMARCHE EVS'!B6 -> 675000 | J76: Installation nouveaux ponts | K76: =IF(F76>2008,"Evaluation interne", " ") | L76: =IF(F76>2008, F76+20, " ") | M76: N | N76: 2027 | O76: 40000 | W76: =40000 + 25000 -> 65000 | AB76: 860000 | BD76: EGT | BJ76: Pont RA Nord 32T CHSL | BM76: 2028 | BQ76: Intégrateur : 20 K€
A77: 1-FRANCE | B77: UPL | C77: Pont AF3 32T SAMETO | E77: Stockage outils | F77: 1971 | H77: =IF(F77="","",YEAR(TODAY())-F77) -> 55 | I77: ='DEMARCHE EVS'!B6 -> 675000 | M77: N | N77: 2026 | O77: 40,00 | T77: 40000 | AA77: 170000
A78: 1-FRANCE | B78: UPL | C78: Pont AB6. FLC/SAMETO. 50T | D78: Pince | E78: L62 | F78: 1969 | G78: rénovation en 2000 | H78: =IF(F78="","",YEAR(TODAY())-F78) -> 57 | I78: ='DEMARCHE EVS'!B8 -> 840000 | J78: RGE | K78: =IF(F78>2008,"Evaluation interne", " ") | L78: =IF(F78>2008, F78+20, " ") | M78: O | N78: 2027 | O78: 40000 | Q78: 50000 | W78: 40000 | BJ78: Pont AB6. FLC/SAMETO. 50T | BK78: Manutention | BM78: 2025
A79: 1-FRANCE | B79: UPL | C79: Pont AB4 Nord 15T APLEVAGE | D79: Elingue | E79: X | F79: 1958 | H79: =IF(F79="","",YEAR(TODAY())-F79) -> 68 | I79: 150000 | K79: =IF(F79>2008,"Evaluation interne", " ") | L79: =IF(F79>2008, F79+20, " ") | M79: O | N79: 2028 | T79: 4300 | Z79: 4300 | BD79: EGT | BJ79: Pont AB4 Nord 15T APLEVAGE | BM79: asap
A80: 1-FRANCE | B80: UPL | C80: Pont AA4 6T APLEVAGE | D80: Elingue | E80: MAINTENANCE | F80: 1958 | H80: =IF(F80="","",YEAR(TODAY())-F80) -> 68 | I80: ='DEMARCHE EVS'!B4 -> 70000 | K80: =IF(F80>2008,"Evaluation interne", " ") | L80: =IF(F80>2008, F80+20, " ") | M80: O | N80: 2025 | O80: 8000 | Q80: 8000 | AF80: 8000 | BJ80: Pont AA4 6T APLEVAGE | BM80: asap | BQ80: Done
A81: 1-FRANCE | B81: UPL | C81: Pont AB4 sud 15T APLEVAGE | D81: Elingue | E81: L43 MP | F81: 1957 | H81: =IF(F81="","",YEAR(TODAY())-F81) -> 69 | I81: 150000 | K81: =IF(F81>2008,"Evaluation interne", " ") | L81: =IF(F81>2008, F81+20, " ") | M81: O | N81: 2028 | T81: 4300 | Z81: 4300 | BJ81: Pont AB4 sud 15T APLEVAGE | BM81: asap | BQ81: - Bouées de détection assymétrique
A82: 1-FRANCE | B82: UPL | C82: Pont AA2 6T LEVMAN | D82: Elingue | E82: RABOUTEUSES | F82: 1953 | H82: =IF(F82="","",YEAR(TODAY())-F82) -> 73 | K82: =IF(F82>2008,"Evaluation interne", " ") | L82: =IF(F82>2008, F82+20, " ") | M82: à désinvestir > sept 25 | BJ82: Pont AA2 6T LEVMAN | BM82: asap
A83: 2-ESPAGNE | B83: PAL | C83: Pont 45/45T PG7 GH | D83: Elingue | F83: 2021 | H83: =IF(F83="","",YEAR(TODAY())-F83) -> 5 | K83: =IF(F83>2008,"Evaluation interne", " ") -> Evaluation interne | L83: =IF(F83>2008, F83+20, " ") -> 2041 | M83: N | N83: =F83+39 -> 2060 | O83: 40000 | W83: 20000 | BD83: 2026B | BJ83: Pont 45/45T PG7 GH
A84: 2-ESPAGNE | B84: PAL | C84: Pont 45/45T PG5 DEMAG High Speed | D84: Elingue | E84: XL HS | F84: 2017 | H84: =IF(F84="","",YEAR(TODAY())-F84) -> 9 | K84: =IF(F84>2008,"Evaluation interne", " ") -> Evaluation interne | L84: =IF(F84>2008, F84+20, " ") -> 2037 | M84: N | N84: =F84+20 -> 2037 | O84: 40000 | AS84: 170000 | BD84: EGT | BJ84: Pont 45/45T PG5 DEMAG High Speed | BN84: 2025
A85: 2-ESPAGNE | B85: PAL | C85: SP 25/25T SEVAL | D85: Elingue | F85: 2006 | H85: =IF(F85="","",YEAR(TODAY())-F85) -> 20 | J85: RGE 25 ans | K85: =IF(F85>2008,"Evaluation interne", " ") | L85: =IF(F85>2008, F85+20, " ") | M85: N | N85: =F85+39 -> 2045 | O85: 25000 | BJ85: SP 25/25T SEVAL | BK85: Manipulation | BM85: 2029
A86: 2-ESPAGNE | B86: PAL | C86: Pont 32/32T PG4 SEVAL | D86: Elingue | F86: 2005 | H86: =IF(F86="","",YEAR(TODAY())-F86) -> 21 | J86: RGE 25 ans | K86: =IF(F86>2008,"Evaluation interne", " ") | L86: =IF(F86>2008, F86+20, " ") | M86: N | N86: =F86+39 -> 2044 | O86: 40000 | W86: 20000 | AP86: 170000 | BD86: EGT | BJ86: Pont 32/32T PG4 SEVAL | BM86: 2028
A87: 2-ESPAGNE | B87: PAL | C87: Pont 63/63T PG1 SEVAL Matriceria | D87: Elingue | E87: MAINTENANCE | F87: 2004 | H87: =IF(F87="","",YEAR(TODAY())-F87) -> 22 | J87: RGE 25 ans | K87: =IF(F87>2008,"Evaluation interne", " ") | L87: =IF(F87>2008, F87+20, " ") | M87: N | N87: =F87+39 -> 2043 | O87: 40000 | W87: 20000 | AM87: 170000 | BJ87: Pont 63/63T PG1 SEVAL Matriceria | BM87: 2027
A88: 2-ESPAGNE | B88: PAL | C88: Pont 63T PG2 SEVAL L2 | D88: Elingue | E88: L02 | F88: 2002 | H88: =IF(F88="","",YEAR(TODAY())-F88) -> 24 | J88: RGE 25 ans | K88: =IF(F88>2008,"Evaluation interne", " ") | L88: =IF(F88>2008, F88+20, " ") | M88: N | N88: =F88+39 -> 2041 | O88: 40000 | W88: 20000 | AG88: 170000 | BD88: EGT | BJ88: Pont 63T PG2 SEVAL L2 | BM88: 2026
A89: 2-ESPAGNE | B89: PAL | C89: Pont 63T PG3 SEVAL L3 et 4 | D89: Elingue | E89: L03/L04 | F89: 2002 | H89: =IF(F89="","",YEAR(TODAY())-F89) -> 24 | I89: 1100000 | J89: RGE 25 ans | K89: =IF(F89>2008,"Evaluation interne", " ") | L89: =IF(F89>2008, F89+20, " ") | M89: N | N89: =F89+39 -> 2041 | O89: 40000 | U89: 329000 | W89: 20000 | AG89: 170000 | BD89: EGT | BE89: RPM S23 - att expertise | BJ89: Pont 63T PG3 SEVAL L3 et 4 | BM89: 2026
A90: 2-ESPAGNE | B90: PAL | C90: Pont 63/63T PG6 DEMAG | D90: Elingue | F90: 2001 | H90: =IF(F90="","",YEAR(TODAY())-F90) -> 25 | J90: RGE 25 ans | K90: =IF(F90>2008,"Evaluation interne", " ") | L90: =IF(F90>2008, F90+20, " ") | M90: N | N90: =F90+39 -> 2040 | O90: 40000 | W90: 20000 | AD90: 170000 | BD90: EGT | BJ90: Pont 63/63T PG6 DEMAG | BM90: 2026
A91: 2-ESPAGNE | B91: VLL | C91: Pont 40 T HOMANSER | F91: 2021 | H91: =IF(F91="","",YEAR(TODAY())-F91) -> 5 | K91: =IF(F91>2008,"Evaluation interne", " ") -> Evaluation interne | L91: =IF(F91>2008, F91+20, " ") -> 2041 | M91: N | N91: =F91+39 -> 2060 | O91: 40000 | BD91: EGT | BJ91: Pont 40 T HOMANSER
A92: 2-ESPAGNE | B92: VLL | C92: Pont 10 T HOMANSER | E92: X | F92: 2021 | H92: =IF(F92="","",YEAR(TODAY())-F92) -> 5 | K92: =IF(F92>2008,"Evaluation interne", " ") -> Evaluation interne | L92: =IF(F92>2008, F92+20, " ") -> 2041 | M92: N | N92: =F92+39 -> 2060 | O92: 40000 | BD92: EGT | BJ92: Pont 10 T HOMANSER
A93: 2-ESPAGNE | B93: VLL | C93: Pont 32 Tnord SEVAL bobines + retrofit DEMAG (2016) | D93: Pince | E93: BOBINES | F93: 2004 | H93: =IF(F93="","",YEAR(TODAY())-F93) -> 22 | J93: RG | K93: =IF(F93>2008,"Evaluation interne", " ") | L93: =IF(F93>2008, F93+20, " ") | M93: N | N93: =F93+39 -> 2043 | O93: 40000 | R93: 110000 | AM93: 170000 | BJ93: Pont 32 Tnord SEVAL bobines + retrofit DEMAG (2016) | BM93: 2025
A94: 2-ESPAGNE | B94: VLL | C94: Pont 32Tsud SEVAL bobines + retrofit DEMAG (2011) | D94: Pince | E94: BOBINES | F94: 2004 | H94: =IF(F94="","",YEAR(TODAY())-F94) -> 22 | J94: RGE | K94: =IF(F94>2008,"Evaluation interne", " ") | L94: =IF(F94>2008, F94+20, " ") | M94: N | N94: =F94+39 -> 2043 | O94: 40000 | R94: 110000 | AM94: 170000 | BJ94: Pont 32Tsud SEVAL bobines + retrofit DEMAG (2011) | BM94: 2025
A95: 2-ESPAGNE | B95: VLL | C95: Pont 32/32 T SEVAL Matricea 13a | D95: Elingue | E95: MAINTENANCE | F95: 2003 | H95: =IF(F95="","",YEAR(TODAY())-F95) -> 23 | J95: RGE | K95: =IF(F95>2008,"Evaluation interne", " ") | L95: =IF(F95>2008, F95+20, " ") | M95: N | N95: =F95+39 -> 2042 | O95: 40000 | AJ95: 170000 | BJ95: Pont 32/32 T SEVAL Matricea 13a | BM95: 2030
A96: 2-ESPAGNE | B96: VLL | C96: Pont 63/63 T SEVAL L13b | D96: Elingue | E96: L13B | F96: 2003 | H96: =IF(F96="","",YEAR(TODAY())-F96) -> 23 | J96: RGE | K96: =IF(F96>2008,"Evaluation interne", " ") | L96: =IF(F96>2008, F96+20, " ") | M96: N | N96: =F96+39 -> 2042 | O96: 40000 | AJ96: 170000 | BD96: EGT | BJ96: Pont 63/63 T SEVAL L13b | BM96: 2030
A97: 2-ESPAGNE | B97: VLL | C97: Pont 32/32 T SEVAL L11 | D97: Elingue | E97: L11 | F97: 2002 | H97: =IF(F97="","",YEAR(TODAY())-F97) -> 24 | J97: RGE | K97: =IF(F97>2008,"Evaluation interne", " ") | L97: =IF(F97>2008, F97+20, " ") | M97: N | N97: =F97+39 -> 2041 | O97: 40000 | AG97: 170000 | BD97: EGT | BJ97: Pont 32/32 T SEVAL L11 | BM97: 2029
A98: 2-ESPAGNE | B98: VLL | C98: Pont 63/63 T SEVAL L15 | D98: Elingue | E98: L15 | F98: 2002 | H98: =IF(F98="","",YEAR(TODAY())-F98) -> 24 | J98: RGE | K98: =IF(F98>2008,"Evaluation interne", " ") | L98: =IF(F98>2008, F98+20, " ") | M98: N | N98: =F98+39 -> 2041 | O98: 40000 | AG98: 170000 | BD98: EGT | BJ98: Pont 63/63 T SEVAL L15 | BM98: 2029
A99: 2-ESPAGNE | B99: VLL | C99: Pont 32/32 T SEVAL L5 | D99: Elingue | E99: L5/L6 | F99: 2001 | H99: =IF(F99="","",YEAR(TODAY())-F99) -> 25 | J99: RGE 25 ans | K99: =IF(F99>2008,"Evaluation interne", " ") | L99: =IF(F99>2008, F99+20, " ") | M99: N | N99: =F99+39 -> 2040 | O99: 40000 | AD99: 170000 | BD99: 2026 | BJ99: Pont 32/32 T SEVAL L5 | BM99: 2028 | BN99: 2025 | BO99: changement chef de dpt 16/04/25
A100: 2-ESPAGNE | B100: VLL | C100: Pont 32/32 T SEVAL L17 | D100: Elingue | E100: PPT L17 | F100: 2001 | H100: =IF(F100="","",YEAR(TODAY())-F100) -> 25 | J100: RGE 25 ans | K100: =IF(F100>2008,"Evaluation interne", " ") | L100: =IF(F100>2008, F100+20, " ") | M100: N | N100: =F100+39 -> 2040 | O100: 40000 | AD100: 170000 | BD100: EGT | BJ100: Pont 32/32 T SEVAL L17 | BM100: 2028
A101: 2-ESPAGNE | B101: VLL | C101: Pont 63/63 T ARAEL L1 | D101: Elingue | E101: L1 | F101: 2000 | H101: =IF(F101="","",YEAR(TODAY())-F101) -> 26 | J101: RGE | K101: =IF(F101>2008,"Evaluation interne", " ") | L101: =IF(F101>2008, F101+20, " ") | M101: N | N101: =F101+39 -> 2039 | O101: 40000 | AA101: 170000 | BD101: EGT | BJ101: Pont 63/63 T ARAEL L1 | BM101: 2027
...

Sheet SYNTHESE ANNEE-5ans-10 ans
A1: =Ponts!R206 -> 0 | B1: =Ponts!S206 -> 0 | C1: =Ponts!T206 -> 0 | D1: =Ponts!U206 -> 0 | E1: =Ponts!V206 -> 0 | F1: =Ponts!W206 -> 2026 OPEX DF (EVS et travaux préconisés) | G1: =Ponts!X206 -> 2026 RGE/RGM CAPEX IV | H1: =Ponts!Y206 -> 2026 ACHAT NEUF CAPEX IV | ... AO1: =Ponts!BF206 -> 2037 ACHAT NEUF CAPEX IV
A2: =Ponts!R207 -> TOUS SITES | B2: =Ponts!S207 -> 0 | C2: =Ponts!T207 -> 372000 | D2: =Ponts!U207 -> 455000 | E2: =Ponts!V207 -> 0 | F2: =Ponts!W207 -> 656600 | G2: =Ponts!X207 -> 834000 | H2: =Ponts!Y207 -> 740000 | ... AO2: =Ponts!BF207 -> 0
A3: =Ponts!R208 -> CHASSIS | B3: =Ponts!S208 -> 0 | C3: =Ponts!T208 -> 0 | D3: =Ponts!U208 -> 0 | E3: =Ponts!V208 -> 0 | F3: =Ponts!W208 -> 0 | G3: =Ponts!X208 -> 420000 | H3: =Ponts!Y208 -> 0 | ... AO3: =Ponts!BF208 -> 0
A4: =Ponts!R209 -> HORS CHASSIS | B4: =Ponts!S209 -> 0 | C4: =Ponts!T209 -> 0 | D4: =Ponts!U209 -> 0 | E4: =Ponts!V209 -> 0 | F4: =Ponts!W209 -> 656600 | G4: =Ponts!X209 -> 414000 | H4: =Ponts!Y209 -> 740000 | ... AO4: =Ponts!BF209 -> 0
B9: 2027 | C9: 2028 | D9: 2029 | E9: 2030 | F9: 2031 | J9: 2026 | K9: an | L9: 5 ANS | M9: 5 ANS | N9: 10 ANS | O9: 10 ANS
A10: CAP EVS | B10: =$K$10 -> 328000 | C10: =$K$10 -> 328000 | D10: =$K$10 -> 328000 | E10: =$K$10 -> 328000 | F10: =$K$10 -> 328000 | H10: 40000 | I10: EVS à réaliser | J10: =N10/10 -> 8.2 | K10: =$H$10*J10 -> 328000 | L10: 39 | M10: =$H$11*L10 -> 6630000 | N10: 82 | O10: =$H$11*N10 -> 13940000
A11: CAP RGE | B11: =$K$11 -> 1224000 | C11: =$K$11 -> 1224000 | D11: =$K$11 -> 1224000 | E11: =$K$11 -> 1224000 | F11: =$K$11 -> 1224000 | H11: 170000 | I11: RGE 25 ans | J11: =N11/10 -> 7.2 | K11: =$H$11*J11 -> 1224000 | L11: 31 | M11: =L11*H11 -> 5270000 | N11: 72 | O11: =N11*H11 -> 12240000
A12: CAP event gates | B12: =$K$12 -> 1205454.5 | C12: =$K$12 -> 1205454.5 | D12: =$K$12 -> 1205454.5 | E12: =$K$12 -> 1205454.5 | F12: =$K$12 -> 1205454.5 | H12: 80000 | I12: EVENT GATES | J12: =N12/11 -> 7.0909091 | K12: =$H$11*J12 -> 1205454.5 | L12: =5*9 -> 45 | M12: =L12*H12 -> 3600000 | N12: 78 | O12: =N12*H12 -> 6240000
A13: Dépenses OPEX usine (EVS) | B13: =Ponts!Z209 -> 357000 | C13: =Ponts!AC209 -> 188600 | D13: =Ponts!AF209 -> 65000 | E13: =Ponts!AI209 -> 153000 | F13: =Ponts!AL209 -> 5000
A14: OBJECTIF - 0 PONT NEUF | B14: =Ponts!AA209 -> 2810000 | C14: =Ponts!AD209 -> 1160000 | D14: =Ponts!AG209 -> 1190000 | E14: =Ponts!AJ209 -> 1870000 | F14: =Ponts!AM209 -> 1320000 | M14: =SUM(K10:K12) -> 2757454.5 | N14: =SUM(M10:M12) -> 15500000 | O14: =SUM(O10:O12) -> 32420000
A15: CAPEX IV JANVIER | B15: 6740000 | C15: 4070000 | D15: 3470000 | E15: 1950000 | F15: 1950000
A16: CAPEX IV FEV | B16: ='SAUVPonts FEV26'!X210+'SAUVPonts FEV26'!Y210 -> 4595000 | C16: ='SAUVPonts FEV26'!AA210+'SAUVPonts FEV26'!AB210 -> 5060000 | D16: ='SAUVPonts FEV26'!AD210+'SAUVPonts FEV26'!AE210 -> 1190000 | E16: ='SAUVPonts FEV26'!AG210+'SAUVPonts FEV26'!AH210 -> 2570000 | F16: ='SAUVPonts FEV26'!AJ210+'SAUVPonts FEV26'!AK210 -> 2170000
A17: CAPEX IV MARS | B17: =Ponts!AA209+Ponts!AB209 -> 5045000 | C17: =Ponts!AD209+Ponts!AE209 -> 4090000 | D17: =Ponts!AG209+Ponts!AH209 -> 1190000 | E17: =Ponts!AJ209+Ponts!AK209 -> 1870000 | F17: =Ponts!AM209+Ponts!AN209 -> 2170000 | J17: 2026 | K17: 2027 | L17: 2028 | M17: 2029 | N17: 2030 | O17: 2031
A18: CAPEX IV AVRIL | I18: EVS | J18: 656000 | K18: =B13 -> 357000 | L18: =C13 -> 188600 | M18: =D13 -> 65000 | N18: =E13 -> 153000 | O18: =F13 -> 5000
A19: CAPEX IV MAI | I19: GAINS | J19: 740000 | K19: =B16-B14 -> 1785000 | L19: =C16-C14 -> 3900000 | M19: =D16-D14 -> 0 | N19: =E16-E14 -> 700000 | O19: =F16-F14 -> 850000
A20: CAPEX IV JUIN
A21: CAPEX IV JUILLET
A22: CAPEX IV SEPTEMBRE
A23: CAPEX IV OCTOBRE
A24: CAPEX IV NOVEMBRE
A25: CAPEX IV DECEMBRE
B50: BUDGET | C50: POLITIQUE METIER | D50: 2026 | E50: 2027-2031 | F50: 2032-2036
B51: OPEX DF | C51: EVS | D51: =Ponts!W209/1000 -> 656.6 | E51: =Ponts!AB225/1000 -> 768.6 | F51: =Ponts!AQ225/1000 -> 457.5
B52: CAPEX 65307 | C52: RGE RGM | D52: =Ponts!X209/1000 -> 414 | E52: =Ponts!AB226/1000 -> 8350 | F52: =Ponts!AQ226/1000 -> 2340
B53: CAPEX 65307 | C53: ACHAT PONTS NEUFS | D53: =Ponts!Y209/1000 -> 740 | E53: =Ponts!AB227/1000 -> 6015 | F53: =Ponts!AQ227/1000 -> 1120
B54: CAPEX IV | C54: IA | D54: ='EVENT GATES'!E22/1000 -> 499 | E54: ='EVENT GATES'!F22/1000*5 -> 3095 | F54: =E54 -> 3095

Sheet DEMARCHE EVS
A1: à partir de 2006 | B1: 20 ans pour faire EVS sauf exception et à déterminer au cas par cas
A2: avant 2006 | B2: 40 ans
A3: EVS | B3: selon pb : achat pont neuf | E3: RGEM
A4: PONT 5T | B4: 70000
A5: PONT -25T | B5: 500000 | C5: STD RENAULT
A6: PONT 32T | B6: 675000 | C6: STD RENAULT | D6: si standard fournisseur : -50% (FEM < M6) | E6: +20K si dble crochet | F6: 650K/700K
A7: PONT 40T | B7: 725000 | C7: STD RENAULT | D7: si standard fournisseur : -50% (FEM < M6) | E7: +20K si dble crochet | F7: 700K/750K
A8: PONT 50T | B8: 840000 | C8: STD RENAULT | D8: si standard fournisseur : -50% (FEM < M6) | E8: +30K si dble crochet | F8: 800K/880K
A9: PONT 63T | B9: 950000 | C9: STD RENAULT | D9: si standard fournisseur : -50% (FEM < M6) | E9: +30K si dble crochet | F9: 900K/1000K
A10: PONT 63T/32
A11: RGEM 1 CROCHET
A12: RGEM DEUX CROCHETS
A15: année MES | B15: EVS +39 | C15: condition
A16: année MES | B16: EVS +20 (si après 2006) | C16: nb de cycles éffectués / groupe FEM
B17: évaluation interne = enquête Daniel, avec calcul de la durée de vie suputée
B18: ajouter colonne "pont à évaluer en interne" (>MES 2008)par référent levage sur durée de vie passée et restante
